{"Mass.": [1076, {"Stackpole v. Arnold": ["2053443", 6]}, {"Barker v. Prentiss": ["2000782", 5]}, {"Richards v. Dutch": ["2028512", 5]}, {"Smith v. Proprietors of the First Congregational Meetinghouse": ["2013226", 5]}, {"Wilkinson v. Scott": ["2036111", 4]}, {"Weld v. Bartlett": ["2026981", 4]}, {"Dawes v. Head": ["2010327", 4]}, {"Hayward v. Leonard": ["2056593", 4]}, {"Wallis v. Wallis": ["2003825", 4]}, {"Dawes v. Boylston": ["2029743", 4]}], "Va.": [148, {"Royall\u2019s Administrators v. Johnson": ["4443298", 4]}, {"Scott v. Trent": ["6714678", 3]}, {"Chamberlayne v. Temple": ["6714776", 2]}, {"Chapman\u2019s Adm\u2019x v. Turner": ["2094941", 2]}, {"Crabtree v. Horton": ["4442950", 2]}, {"Smith v. Jones": ["6732366", 2]}, {"Whitacre v. M\u2019Ilhaney": ["4442457", 2]}, {"Claiborne v. Parrish": ["6714633", 2]}, {"Barrett & Co. v. Tazewell": ["2094945", 2]}, {"Bogle, Somerville & Co. v. Sullivant": ["2094979", 2]}], "Pa.": [339, {"Lessee of Billington v. Welsh": ["1793579", 2]}, {"Attorney-General v. Grantees under the act of April 1792": ["581251", 2]}, {"Shortz v. Quigley": ["1787875", 2]}, {"Wallace v. Duffield": ["1798244", 2]}, {"Hill v. Ely": ["1804363", 2]}, {"Eberle v. Mayer": ["1819214", 2]}, {"Commonwealth v. Lesher": ["1818176", 2]}, {"Duncan v. Keiffer": ["1791074", 2]}, {"Moore v. Wait": ["1787961", 2]}, {"Patton\u2019s administrators v. Ash": ["1808219", 2]}], "N.Y.": [566, {"King v. Baldwin": ["6065132", 4]}, {"Boyd v. M\u2018Lean": ["1975615", 3]}, {"Walden v. Sherburne": ["2141018", 3]}, {"Pain v. Packard": ["374482", 3]}, {"Borden v. Fitch": ["2141045", 3]}, {"Jackson, ex dem. Clowes v. Vanderheyden": ["6064852", 3]}, {"Steere v. Steere": ["1980809", 3]}, {"King v. Baldwin": ["1178089", 3]}, {"Hayes v. Ward": ["1978845", 3]}, {"Fulton v. Matthews": ["2141026", 3]}], "Conn.": [128, {"Ingraham v. Wheeler": ["6754660", 3]}, {"Sherwood v. Burr": ["6753455", 2]}, {"Aldrich v. Kinney": ["12130031", 2]}, {"Ingraham v. Hutchinson": ["6755609", 2]}, {"Hempstead v. Reed": ["6755503", 2]}, {"Kline v. Beebe": ["6755535", 2]}, {"Brackett v. Norton": ["12134077", 2]}, {"Lyon v. Lyman": ["6754006", 2]}, {"Medbury v. Hopkins": ["6755419", 2]}, {"Inhabitants of Newtown v. Inhabitants of Danbury": ["6755779", 2]}], "Ohio": [36, {"Lessee of Matthews v. Thompson": ["211473", 2]}, {"Spencer v. Brockway": ["1427758", 2]}, {"Earnfit v. Winans": ["211514", 1]}, {"Harvey v. Brown": ["1427755", 1]}, {"Lessee of N. Massie\u2019s Heirs v. Long": ["575718", 1]}, {"Weyer v. Zane": ["211636", 1]}, {"Courcier v. Graham": ["1427767", 1]}, {"Norton v. Beaver": ["579790", 1]}, {"Douglass v. Scott": ["579776", 1]}, {"Jackman v. Hallock": ["1427772", 1]}], "Vt.": [67, {"Roger v. Davis": ["617370", 3]}, {"Reading v. Rockingham": ["8545607", 3]}, {"State v. Squires": ["4414944", 2]}, {"Stanton v. Bannister": ["8546392", 2]}, {"Barney v. Goff": ["2472909", 1]}, {"Aldis v. Johnson": ["8544758", 1]}, {"Paine v. Webster": ["8544745", 1]}, {"Tichout v. Cilley": ["11269785", 1]}, {"Galusha v. Sinclear": ["11269728", 1]}, {"Shumway v. Shumway": ["8545799", 1]}], "S.C.": [52, {"M\u2019Elwee v. Sutton": ["2511281", 2]}, {"Jones v. Cole": ["2511793", 2]}, {"Atkinson v. Hartley": ["8858490", 2]}, {"Coudery v. Zealy": ["2513199", 2]}, {"Bowman v. Middleton": ["9506394", 1]}, {"Wilkinson v. Campbell": ["9505813", 1]}, {"Eden v. Legare": ["9505847", 1]}, {"Lindsay v. Commissioners": ["8672085", 1]}, {"Thayer v. Sheriff of Charleston District": ["8672455", 1]}, {"Dott v. Cunnington": ["9507709", 1]}], "N.C.": [26, {"Clancy v. Dickey": ["11277011", 2]}, {"Hauser v. Mann": ["11276890", 1]}, {"Brocket v. Foscue": ["11275283", 1]}, {"Ingles v. Donaldson": ["11960510", 1]}, {"Doe on demise of Lanier v. Stone": ["11276207", 1]}, {"Executors of Reel v. Reel": ["11275997", 1]}, {"Price v. Sykes": ["11275378", 1]}, {"Powell v. Executor of Powell": ["8695342", 1]}, {"State v. Pugh": ["11960382", 1]}, {"Fitts ex rel. County Trustee v. Hawkins": ["11276732", 1]}], "Ky.": [35, {"Instone v. Williamson": ["6395253", 2]}, {"Rumsey v. Matthews": ["6683357", 2]}, {"Greenup v. Lyne\u2019s Heirs": ["6411476", 2]}, {"Jones v. Bullock": ["6410316", 1]}, {"Scott v. Clarkson's Executrix": ["6684258", 1]}, {"Gregory v. Brown": ["6384342", 1]}, {"Hancock v. Brinker": ["6397614", 1]}, {"Owens v. Gatewood": ["6423036", 1]}, {"Richardson v. Brown": ["6394052", 1]}, {"Commonwealth v. M\u2019Gowan": ["6388493", 1]}], "Ala.": [15, {"Huff v. Campbell": ["8495749", 1]}, {"Johnson ex rel. Stone v. English": ["8493581", 1]}, {"Cato v. Easley": ["3176083", 1]}, {"Tankersley v. Richardson": ["3173169", 1]}, {"Pitts v. Keyser": ["8493485", 1]}, {"Todd v. Stafford": ["8493765", 1]}, {"Gayle v. Singleton": ["8495792", 1]}, {"Winston v. Moseley": ["3172901", 1]}, {"Pettigrew v. Pettigrew": ["8495828", 1]}, {"Brannan v. Oliver": ["3175383", 1]}], "N.H.": [12, {"Southerin v. Mendum": ["6756916", 1]}, {"Henderson v. McDuffee": ["6754978", 1]}, {"Bullen v. Runnels": ["6756362", 1]}, {"Kingsbury v. Pond": ["6755642", 1]}, {"Perkins v. Challis": ["6752925", 1]}, {"Eaton v. Sloan": ["6757482", 1]}, {"Bean v. Quimby": ["6755255", 1]}, {"Makepeace v. Worden": ["6752648", 1]}, {"Shepherd v. Thompson": ["6755898", 1]}, {"Wright v. First Crockery Ware Co.": ["6752986", 1]}], "Tenn.": [10, {"Ragan v. Kennedy": ["12127118", 2]}, {"Bashaw v. Blakemore's Administrator": ["12144646", 1]}, {"Townsend v. Sharp": ["12129028", 1]}, {"State v. Anderson": ["12121358", 1]}, {"Reids Lessee v. Dodson": ["12146647", 1]}, {"Lewis\u2019s Executors v. Hickman\u2019s Heirs & Administrators": ["12135576", 1]}, {"Steele v. M\u2019Kinnie": ["11267095", 1]}, {"Thurmond v. Durham": ["8542395", 1]}, {"Brown v. M\u2018Can": ["6098546", 1]}], "Md.": [7, {"Iglehart v. Armiger": ["1714912", 1]}, {"Jones v. Jones": ["1714911", 1]}, {"Ratrie v. Wheeler\u2019s Ex\u2019r": ["1721431", 1]}, {"Spedden v. State ex rel. Marshall": ["1754838", 1]}, {"Collins v. Elliott": ["11297651", 1]}, {"Jarrett\u2019s Lessee v. Cooler": ["1721244", 1]}, {"Davidson v. Clayland": ["11305579", 1]}], "Mo.": [3, {"Butcher v. Keil": ["8854261", 1]}, {"Blunt v. Sheppard": ["8853793", 1]}, {"Davis v. Hays": ["8854325", 1]}], "Ind.": [5, {"Allen v. Wooley": ["1389510", 1]}, {"Longworth v. Conwell": ["1385405", 1]}, {"Wilson v. Hickson": ["1389566", 1]}, {"Harrison v. Warner": ["1389457", 1]}, {"Hedges v. Gray": ["1389375", 1]}], "La.": [5, {"Melancton\u2019s Heirs v. Broussard": ["8747838", 1]}, {"Rils v. Questi": ["8750529", 1]}, {"Loreau v. Declouet": ["640074", 1]}, {"Nichols v. Hanse": ["8752593", 1]}, {"Stone v. Clifford": ["639897", 1]}]}