{"Mass.": [5763, {"Coombs v. New Bedford Cordage Co.": ["2142929", 11]}, {"Shaw v. Spencer": ["2141777", 10]}, {"Farwell v. Boston & Worcester Rail Road": ["2065782", 9]}, {"Hill v. City of Boston": ["2134634", 8]}, {"Furnas v. Durgin": ["737038", 8]}, {"Chester Glass Co. v. Dewey": ["2035206", 8]}, {"Sweeny v. Old Colony & Newport Railroad": ["2117010", 7]}, {"Hickey v. Boston & Lowell Railroad": ["2138245", 7]}, {"Gannon v. Hargadon": ["2117028", 7]}, {"Allyn v. Boston & Albany Railroad": ["713160", 7]}], "N.Y.": [13301, {"Commercial Bank v. Hughes": ["2020920", 12]}, {"New York & New Haven Railroad v. Schuyler": ["16535", 12]}, {"Bissell v. Michigan Southern & Northern Indiana Railroad Companies": ["2026262", 11]}, {"People v. Cook": ["2010488", 11]}, {"Spear v. Crawford": ["2017119", 11]}, {"Dash v. Van Kleeck": ["369188", 10]}, {"Farmers & Mechanics\u2019 Bank v. Butchers & Drovers\u2019 Bank": ["1297799", 9]}, {"Mc\u2019Cartee v. Orphan Asylum Society": ["2159612", 9]}, {"McNeil v. Tenth National Bank": ["2052673", 9]}, {"Brown v. Bowen": ["2040665", 9]}], "Pa.": [2295, {"Lauman v. Lebanon Valley Railroad": ["415549", 6]}, {"Wusthoff v. Dracourt": ["1841321", 6]}, {"Patterson v. Pittsburg & Connellsville Railroad": ["1038917", 5]}, {"Heeter v. Glasgow": ["438399", 5]}, {"Philadelphia & Reading Railroad v. Spearen": ["485547", 5]}, {"Kay v. Pennsylvania Railroad": ["430596", 5]}, {"Commonwealth ex rel. Hamilton v. Select & Common Councils": ["418009", 4]}, {"North Pennsylvania Railroad v. Heileman": ["998459", 4]}, {"Wheatley v. Baugh": ["975872", 4]}, {"Shamokin Valley Railroad v. Livermore": ["485591", 4]}], "Miss.": [1380, {"Harman v. Hoskins": ["11259995", 7]}, {"Roach v. Brannon": ["8840058", 5]}, {"New Orleans, St. Louis & Chicago Railroad v. Burke": ["1670064", 4]}, {"Vicksburg & Meridian R. R. v. Ragsdale": ["9514960", 4]}, {"Swann v. Buck": ["9512202", 4]}, {"Summers v. A. Roos & Co.": ["297321", 4]}, {"Harrington v. Wofford": ["9512659", 4]}, {"Green v. Weller": ["11262037", 4]}, {"Hilliard v. Cagle": ["9514363", 4]}, {"Farmers' Bank v. Douglass": ["11263114", 4]}], "Ind.": [7019, {"Fort Wayne, Jackson & Saginaw R. R. v. Husselman": ["1516670", 17]}, {"Fletcher v. Holmes": ["1460685", 16]}, {"Board of Commissioners v. Hall": ["1934974", 16]}, {"Ex parte Walls": ["1942125", 12]}, {"Myers v. Murphy": ["1500644", 12]}, {"Splahn v. Gillespie": ["1414648", 12]}, {"Stott v. Smith": ["1934915", 12]}, {"Bowen v. Pollard": ["1936536", 12]}, {"Graham v. State ex rel. Board of Commissioners": ["1514304", 11]}, {"Potter v. Smith": ["1445082", 11]}], "Mo.": [2968, {"Cunningham v. Hannibal & St. Joseph Railroad": ["8851501", 8]}, {"State ex rel. Missouri & Mississippi Railroad v. Macon County Court": ["958395", 7]}, {"Luckie v. Chicago & Alton Railroad": ["959794", 7]}, {"Pacific Railroad v. Seely": ["11741209", 6]}, {"State v. Hopper": ["451567", 6]}, {"Fletcher v. Atlantic & Pacific Railroad": ["968467", 5]}, {"Gibson v. Pacific Railroad": ["8851018", 5]}, {"Lackland v. North Missouri Railroad": ["996068", 5]}, {"Isabel v. Hannibal & St. Joseph Railroad": ["946191", 5]}, {"State v. Holme": ["973781", 5]}], "Ohio": [1223, {"Henry v. Vermillion & Ashland Rail Road": ["496201", 9]}, {"Mad River & Lake Erie Railroad v. Barber": ["509776", 7]}, {"Kellogg v. Ely": ["524676", 6]}, {"Cleveland, Columbus, Cincinnati & Indianapolis Railway Co. v. Elliott": ["894652", 6]}, {"N. W. Graham & Co. v. W. H. Davis & Co.": ["507508", 6]}, {"Fee v. Big Sand Iron Co.": ["8843133", 5]}, {"Shroyer v. Richmond": ["879704", 5]}, {"Harvey v. Childs & Potter": ["894707", 5]}, {"Cinncinnati, Wilmington & Zanesville Railroad v. Commissioners of Clinton County": ["501916", 4]}, {"State ex rel. Commissioners of Guernsey County v. Findley": ["588149", 4]}], "Conn.": [1023, {"Hooker v. New-Haven & Northampton Co.": ["6754048", 7]}, {"Hayden v. Smithville Manufacturing Co.": ["530645", 7]}, {"Farmers & Citizens\u2019 Bank v. Payne": ["523350", 6]}, {"State v. Carroll": ["759975", 5]}, {"Farrel Foundry v. Dart": ["525343", 5]}, {"State v. Hartford & New Haven Railroad": ["530617", 4]}, {"Bouton v. American Mutual Life Insurance": ["523407", 4]}, {"Mann v. Cooke": ["6755240", 4]}, {"Ward v. Griswoldville Manufacturing Co.": ["12131662", 4]}, {"Wadsworth v. Tillotson": ["6754434", 4]}], "Me.": [1677, {"Brown v. Chadbourne": ["620207", 4]}, {"Bangor & Piscataquis Railroad v. McComb": ["661131", 4]}, {"Sturdivant v. Hull": ["8846005", 4]}, {"Franklin Co. v. Lewiston Institution for Savings": ["8843884", 4]}, {"Knight v. Portland, Saco & Portsmouth Railroad": ["667009", 4]}, {"Goddard v. Grand Trunk Railway": ["634568", 4]}, {"Shanny v. Androscoggin Mills": ["8845022", 4]}, {"Barnes v. Union Mut. Fire Ins.": ["665416", 4]}, {"Skowhegan Bank v. Cutler": ["621810", 4]}, {"Cram v. Bangor House Proprietary": ["1523873", 4]}], "Iowa": [1555, {"Smith & Co. v. McLean": ["2285897", 6]}, {"Viele v. Germania Insurance": ["2284467", 6]}, {"State ex rel. Rice v. County Judge": ["341629", 5]}, {"Gokey v. Knapp": ["103844", 5]}, {"Lyman v. Cessford": ["2293418", 5]}, {"Pursley v. Hayes": ["2287337", 5]}, {"Taylor & Co. v. Kier": ["2318246", 5]}, {"McDonald v. Chicago & N. W. R. R.": ["2284443", 4]}, {"Ayres v. Hartford Fire Insurance": ["9505459", 4]}, {"Greenleaf v. Illinois Central Railroad": ["2281532", 4]}], "N.J.": [341, {"Brown v. Vandyke": ["524044", 3]}, {"Cross v. Mayor of Morristown": ["805217", 3]}, {"Muir v. Newark Savings Institution": ["514212", 3]}, {"Derrickson v. Smith": ["372071", 3]}, {"Barnes v. Trenton Gas Light Co.": ["536579", 2]}, {"Brown v. Hendrickson": ["351424", 2]}, {"Speer v. Speer": ["802757", 2]}, {"National Bank of the Metropolis v. Sprague": ["526156", 2]}, {"Warp v. Cooke": ["511196", 2]}, {"Somerville & Easton Railroad v. Doughty": ["399089", 2]}], "W. Va.": [270, {"Radford v. Carwile": ["8641188", 6]}, {"Hill v. Proctor": ["8641278", 4]}, {"Western M. & M. Co. v. Virginia Cannel Coal Co.": ["8641357", 4]}, {"Neely v. Jones": ["8641159", 3]}, {"Snyder v. P., C. & St. L. Railway Co.": ["8640996", 3]}, {"Merchants\u2019 & Mechanics\u2019 Bank of Wheeling v. Evans": ["8641444", 3]}, {"Bell's Admr. v. Humphrey": ["8641374", 3]}, {"Vance v. Evans": ["8641213", 3]}, {"Osburn v. Staley": ["8641467", 2]}, {"Goshorn v. Board of Supervisors": ["8641822", 2]}], "Wis.": [2127, {"Pettigrew v. Village of Evansville": ["11284893", 8]}, {"Knowlton v. Board of Supervisors": ["8712520", 7]}, {"Weeks v. City of Milwaukee": ["8708764", 7]}, {"Sutton v. Town of Wauwatosa": ["8706043", 6]}, {"Weymouth v. Chicago & North-Western Railway Co.": ["8709774", 5]}, {"Pringle v. Dunn": ["8708135", 5]}, {"Arimond v. Green Bay & Mississippi Canal Co.": ["8707919", 5]}, {"Hoyt v. City of Hudson": ["11285881", 5]}, {"Dyer v. Gibson": ["11286379", 5]}, {"Farmers\u2019 Loan & Trust Co. v. Commercial Bank": ["8708861", 5]}], "Va.": [1021, {"Balt. & Ohio R. R. v. Wightman\u2019s Adm\u2019r": ["6732782", 6]}, {"Davis v. Christian": ["6730993", 5]}, {"Clevinger v. Miller": ["6740976", 5]}, {"Beverley v. Brooke": ["4374719", 4]}, {"Corbin v. Mills' Ex'ors": ["4436246", 4]}, {"Simmons v. Simmons\u2019 Adm\u2019r": ["6715944", 4]}, {"Skipwith's Ex'or v. Cunningham": ["6717450", 4]}, {"Parramore v. Taylor": ["4451169", 4]}, {"Chrisman\u2019s Adm\u2019x v. Harman": ["6733014", 4]}, {"Balt. & Ohio R. R. v. Gallahue\u2019s Adm\u2019rs": ["6716360", 4]}], "Ill.": [4972, {"City of Galena v. Corwith": ["5227561", 9]}, {"St. Louis, Alton & Terre Haute R. R. v. Manly": ["5236204", 9]}, {"J. B. Lyon & Co. v. Culbertson, Blair & Co.": ["2657584", 7]}, {"Evans v. George": ["2683004", 7]}, {"Harper v. Ely": ["5309292", 6]}, {"Tuck v. Downing": ["5315093", 6]}, {"Pickering v. Cease": ["2687743", 6]}, {"Chicago & North Western Railroad v. Swett": ["424991", 6]}, {"Chicago & Rock Island Railroad v. McKean": ["426061", 6]}, {"Illinois Central Railroad v. Godfrey": ["5309299", 6]}], "Tex.": [1532, {"Howard v. North": ["6768777", 7]}, {"Bishop v. State": ["2124181", 6]}, {"Mims v. Mitchell": ["6770973", 5]}, {"Gee v. Scott": ["2155661", 5]}, {"Pearson v. Flanagan": ["2147224", 5]}, {"Gillian v. Henderson": ["2052136", 5]}, {"Shepherd v. Cassiday": ["2121388", 4]}, {"Horan v. Wahrenberger": ["6768732", 4]}, {"Stroud v. Casey": ["2109943", 4]}, {"Withers v. Patterson": ["2105508", 4]}], "N.C.": [1367, {"Mebane v. Mebane": ["8684316", 8]}, {"Attorney General ex rel. Eason v. Perkins": ["8684064", 5]}, {"Williams v. Maitland": ["2096961", 4]}, {"Kidder v. McIlhenny": ["8685971", 4]}, {"State v. Swepson": ["8683331", 4]}, {"Lord v. Beard": ["8683708", 4]}, {"Welfare v. Thompson": ["11277549", 3]}, {"State ex rel. Cox v. Blair": ["8684917", 3]}, {"Swaim v. Stafford": ["8694458", 3]}, {"Bunting v. Ricks": ["8686743", 3]}], "N.H.": [1683, {"Blasdel v. Locke": ["471300", 6]}, {"Pierce v. Emery": ["4519782", 6]}, {"Horn v. Cole": ["11250617", 6]}, {"Eaton v. B. C. & M. R. R.": ["11251573", 5]}, {"Britton v. Turner": ["6756960", 5]}, {"Stewart v. Emerson": ["471354", 5]}, {"Stevens v. Dennett": ["11250787", 5]}, {"Odlin v. Gove": ["8711768", 5]}, {"Smith v. Bean": ["4400531", 5]}, {"Davis v. Handy": ["4536152", 5]}], "Ala.": [2996, {"Fretwell v. McLemore": ["5638738", 8]}, {"Chapman v. Abrahams": ["904007", 7]}, {"Crawford v. Kirksey": ["8492751", 6]}, {"Foster v. Trustees of the Athen\u00e6um": ["8495787", 6]}, {"Gunter v. Leckey": ["8498388", 6]}, {"Cross v. State": ["906046", 6]}, {"Abney v. Kingsland & Co.": ["11256574", 5]}, {"Sadler v. Langham": ["8496013", 5]}, {"Childress v. Monette": ["5612867", 5]}, {"Drake v. Glover": ["8497662", 5]}], "Nev.": [131, {"Solen v. Virginia & Truckee Railroad": ["4624797", 3]}, {"State ex rel. Ash v. Parkinson": ["8576914", 2]}, {"Meagher v. County of Storey": ["8577502", 2]}, {"State v. Waterman": ["8848191", 2]}, {"Johnson v. Wells, Fargo & Co.": ["11273525", 2]}, {"Humboldt County v. County Commissioners": ["11272779", 2]}, {"Steel v. Steel": ["8847438", 2]}, {"Western Union Telegraph Co. v. Atlantic & Pacific States Telegraph Co.": ["8577137", 2]}, {"State v. Silver": ["4618706", 2]}, {"State v. McClear": ["4621414", 2]}], "Mich.": [1581, {"Lake Shore & Michigan Southern Railroad v. Miller": ["1311036", 9]}, {"People ex rel. Detroit & Howell Railroad v. Township Board": ["1939933", 7]}, {"Slater v. Breese": ["1343752", 7]}, {"Bullock v. Taylor": ["1333071", 6]}, {"Youngblood v. Sexton": ["8721267", 6]}, {"Smith v. Shelden": ["1317477", 6]}, {"Hayes v. Livingston": ["1345372", 6]}, {"Chicago & Northwestern Railway Co. v. Bayfield": ["1341600", 5]}, {"Final v. Backus": ["1942858", 5]}, {"Allison v. Chandler": ["1918157", 5]}], "Cal.": [1769, {"Argenti v. City of San Francisco": ["2279307", 6]}, {"McMinn v. Whelan": ["2242280", 5]}, {"Dean v. Davis": ["2336999", 5]}, {"Thornburgh v. Hand": ["2236905", 4]}, {"Martin v. Zellerbach": ["2246123", 4]}, {"Mokelumne Hill Canal & Mining Co. v. Woodbury": ["2238289", 4]}, {"Shea v. Potrero & Bay View Railroad": ["2316165", 4]}, {"People v. Lynch": ["2336930", 4]}, {"Doll v. Meador": ["2279315", 4]}, {"City of San Francisco v. Lawton": ["2301038", 4]}], "Minn.": [489, {"Brown v. Milwaukee & St. Paul Railway Co.": ["561880", 5]}, {"Third National Bank v. Armstrong": ["765697", 4]}, {"Drymala v. Thompson": ["754249", 4]}, {"Nesbitt v. St. Paul Lumber Co.": ["738488", 3]}, {"Johnson v. Carpenter": ["8875408", 3]}, {"Bailey v. Mason": ["745351", 3]}, {"Horton v. Williams": ["738496", 3]}, {"O\u2019Brien v. City of St. Paul": ["765809", 3]}, {"Bingham v. Board of Supervisors of Winona County": ["8876023", 3]}, {"Griggs v. Fleckenstein": ["8875202", 3]}], "Vt.": [1583, {"Law v. Town of Fairfield": ["2354266", 6]}, {"Sprague v. Smith": ["8545105", 6]}, {"Howard v. Windham County Savings Bank": ["748219", 5]}, {"Trow v. Vermont Central Railroad": ["4426807", 5]}, {"Kent v. Town of Lincoln": ["2354727", 5]}, {"Hodge v. Town of Bennington": ["744361", 5]}, {"Langdon v. Town of Castleton": ["741901", 4]}, {"Snow v. Parsons": ["2356794", 4]}, {"Sparhawk v. Administrator of Ozias Buell": ["4416380", 4]}, {"Hurlburt v. Green": ["8545460", 4]}], "Kan.": [636, {"Kansas Pacific Railway Co. v. Pointer": ["66836", 5]}, {"Golden v. Cockril": ["63949", 5]}, {"Bowman v. Cockrill": ["78400", 4]}, {"St. Joseph & Denver City Railroad v. Chase": ["603484", 4]}, {"Leavenworth, Lawrence & Galveston Railroad v. Rice": ["598454", 4]}, {"Hixon v. George": ["48254", 4]}, {"Kansas Pacific Railway Co. v. Cutter": ["588255", 4]}, {"Parsons Savings Bank v. Sargent": ["607024", 4]}, {"Fairbanks v. Williams": ["71913", 4]}, {"Craft v. Com'rs Jackson Co.": ["76452", 3]}], "La.": [340, {"Seibrecht v. City of New Orleans": ["573223", 3]}, {"Hodge v. Cleary": ["8750565", 3]}, {"Bludworth v. Hunter": ["2510840", 3]}, {"Municipality No. Two v. Dunn": ["11958409", 2]}, {"Louisiana State Lottery Co. v. Richoux": ["5227758", 2]}, {"Delahoussaye v. Judice": ["5199568", 2]}, {"Thomas v. Scott": ["2528866", 2]}, {"Yeatman v. Crandall": ["11263585", 2]}, {"McRae v. Chapman": ["2506251", 2]}, {"Plicque & Lebeau v. Perret": ["8749102", 2]}], "Md.": [956, {"Hoffman Steam Coal Co. v. Cumberland Coal & Iron Co.": ["1865350", 5]}, {"Gardner v. Merritt": ["1772607", 4]}, {"United States Telegraph Co. v. Gildersleve": ["1766701", 4]}, {"Ward v. Hollins": ["1862179", 4]}, {"Fell v. State": ["1846905", 4]}, {"State v. Mace": ["1696651", 4]}, {"Scott v. Fox": ["1862214", 4]}, {"Adams v. Michael": ["1840726", 4]}, {"Todd v. Grove": ["1770580", 4]}, {"United States Insurance v. Shriver": ["1687161", 4]}], "Tenn.": [718, {"Washington v. Mayor of Nashville": ["11266748", 5]}, {"Whyte v. Mayor of Nashville": ["8541084", 4]}, {"Union Bank v. State": ["8542991", 3]}, {"Kincannon v. Carroll": ["8541467", 3]}, {"Nelson v. Allen": ["11267285", 3]}, {"Dickson v. Dickson\u2019s Heirs": ["11266539", 3]}, {"Stamper v. Temple": ["11266333", 3]}, {"Mitchell v. Lipe": ["8541886", 3]}, {"Hendrick v. Stewart": ["12148322", 3]}, {"Bell v. Speight": ["11267987", 2]}], "Neb.": [248, {"Dundy v. Board of County Commissioners": ["2882709", 6]}, {"Hurford v. City of Omaha": ["2864978", 4]}, {"Meyer v. Midland Pacific Railroad": ["2857933", 4]}, {"Cheney v. White": ["5376997", 4]}, {"Clendenning v. Crawford & McLaughlin": ["5380325", 3]}, {"Wood v. Helmer": ["588597", 3]}, {"Derby v. Weyrich": ["2882749", 3]}, {"South Platte Land Co. v. Board of County Commissioners": ["5380460", 3]}, {"Philo v. Butterfield": ["2863397", 3]}, {"McCleery v. Allen": ["5379432", 3]}], "Ky.": [647, {"Wing v. Hayden": ["4389305", 5]}, {"City of Lexington v. McQuillan\u2019s Heirs": ["8521204", 4]}, {"Thompson v. Heffner\u2019s executors": ["1309780", 4]}, {"Clark v. McKenzie": ["4383620", 3]}, {"Lexington & Ohio Rail Road v. Applegate": ["4431541", 3]}, {"Tracy v. Hornbuckle": ["6056683", 3]}, {"Ferguson v. Landram": ["2342453", 3]}, {"Allen v. Perry": ["2344162", 3]}, {"Bell v. Offutt": ["4389040", 3]}, {"Cheek v. Commonwealth": ["4395592", 3]}], "Ark.": [556, {"Worthen v. Badgett": ["1877174", 5]}, {"Redmond v. State": ["1872400", 3]}, {"Holliday Bros. v. Cohen": ["1875680", 3]}, {"Porter v. Clements": ["8728559", 3]}, {"Kaufman & Co. v. Stone": ["1864538", 3]}, {"Chambers v. Sallie": ["1882906", 3]}, {"Bourland v. Skimnee": ["8727967", 3]}, {"Stanton v. State": ["8728129", 3]}, {"Howard v. State": ["1875603", 3]}, {"State ex rel. State Bank v. Martin": ["1869328", 3]}], "Ga.": [812, {"Hightower v. Thornton": ["1385633", 5]}, {"Potts v. House": ["583329", 4]}, {"Whittington v. Doe ex dem. Wright": ["591585", 3]}, {"Crawford ex rel. Stanford v. Word": ["580131", 3]}, {"Robinson v. Bank of Darien": ["587186", 3]}, {"Lane v. Latimer": ["849080", 3]}, {"Hudson v. Mayor of Marietta": ["55332", 3]}, {"Howard v. Durand": ["286427", 3]}, {"Taylor v. Johnson ex rel. A. W. & W. P. Carmichael": ["1381427", 3]}, {"Bibb County Loan Ass'n v. Richards": ["270935", 3]}], "R.I.": [171, {"L. Cook & Co. v. Corthell": ["1329090", 5]}, {"Hodges v. New England Screw Co.": ["732300", 4]}, {"Clarke v. School District No. 7": ["8519468", 4]}, {"Aldrich v. Martin": ["720669", 3]}, {"Inman v. Tripp": ["1329116", 3]}, {"Tillinghast v. Champlin": ["720657", 2]}, {"Diman v. Providence, Warren, & Bristol, Railroad": ["8519007", 2]}, {"Philip Allen & Sons v. Woonsocket Co.": ["1329092", 2]}, {"Wilson v. Conway Fire Insurance": ["720667", 2]}, {"Dyer v. Osborne": ["1329009", 2]}], "Fla.": [81, {"Wade v. Doyle": ["6101691", 3]}, {"Prescott v. Johnson": ["1129289", 2]}, {"Lines v. Darden": ["1167642", 2]}, {"Southern Life Insurance & Trust Co. v. Lanier": ["1167656", 2]}, {"McKay v. Lane": ["1167640", 2]}, {"Dixon v. State": ["1159172", 1]}, {"Wilson v. Hayward": ["8849277", 1]}, {"Hollingsworth v. Handcock": ["1130221", 1]}, {"Harrison v. Roberts": ["1168142", 1]}, {"Sanderson\u2019s Administrators v. Sanderson": ["6105777", 1]}], "Dakota Territory": [3, {"Territory v. Conrad": ["8586867", 1]}, {"People v. Sweetser": ["8586818", 1]}, {"McCall v. United States": ["8586827", 1]}], "Wyo.": [2, {"Territory of Wyoming v. Ritter": ["5271194", 1]}, {"Bonnifield v. Price": ["5271556", 1]}], "Or.": [42, {"Northcut v. Lemery": ["2299990", 1]}, {"Strong v. Barnhart": ["2296792", 1]}, {"Board of Commissioners v. Babcock": ["2295316", 1]}, {"Farley v. Parker": ["2296817", 1]}, {"Tippin v. Ward": ["2295317", 1]}, {"Cooper v. McGgrew": ["2300044", 1]}, {"Howe v. Taylor": ["2296782", 1]}, {"Orton v. Orton": ["2298065", 1]}, {"Wilson v. McEwan": ["2298086", 1]}, {"State ex rel. Mahoney v. McKinnon": ["2299969", 1]}], "Colo.": [18, {"Molandin v. Colorado Central Railroad": ["191677", 1]}, {"Gillett v. Gaffney": ["191675", 1]}, {"City of Denver v. Clements": ["191560", 1]}, {"People v. Keeling": ["5288962", 1]}, {"Christ v. People": ["191603", 1]}, {"Cooper v. American Central Ins.": ["191732", 1]}, {"Freas v. Engelbrecht": ["191634", 1]}, {"Wells v. Caywood": ["191713", 1]}, {"Coon v. Rigden": ["5287556", 1]}, {"Brown v. Willoughby": ["193379", 1]}], "S.C.": [424, {"Taylor v. Hampton": ["8857383", 3]}, {"Evans v. Godbold": ["8713273", 3]}, {"Long v. Cason": ["8713405", 3]}, {"Durant v. Ashmore": ["8857986", 3]}, {"Sims v. McLure": ["8713410", 3]}, {"Williams v. Evans": ["220495", 3]}, {"Langston v. South Carolina Railroad": ["8716118", 2]}, {"Ingram v. Belk": ["8486456", 2]}, {"State ex rel. Attorney General v. Platt": ["8715715", 2]}, {"Duncan v. Barnett": ["359597", 2]}], "Mont.": [14, {"Allport v. Kelley": ["8588007", 2]}, {"Chumasero v. Vial": ["11254092", 2]}, {"Vantilburg v. Black": ["11254287", 2]}, {"Missoula County v. Edwards": ["11253286", 1]}, {"Territory v. Perkins": ["8588493", 1]}, {"Territory of Montana v. McClin": ["2284016", 1]}, {"Ryan v. Gilmer": ["8588660", 1]}, {"Deer Lodge County v. Kohrs": ["8587347", 1]}, {"Kleinschmidt v. Dunphy": ["2283972", 1]}, {"Carrhart v. Montana Mineral Land & Mining Co.": ["2283947", 1]}], "Del.": [29, {"State v. Tootle": ["1866257", 2]}, {"Regan v. McCormick": ["1864876", 1]}, {"Doe v. Roe": ["1858924", 1]}, {"Cook v. Gray": ["1860351", 1]}, {"Mayor of Wilmington v. Horn": ["1866234", 1]}, {"Pickering v. Day": ["456892", 1]}, {"Warner v. Allee": ["457855", 1]}, {"Parke v. Blackiston": ["8878783", 1]}, {"Rice v. Foster": ["1864944", 1]}, {"West v. Shockley": ["1864878", 1]}], "D.C.": [4, {"Ould v. Washington Hospital": ["2481317", 1]}, {"Burnstine v. Ormes": ["2485105", 1]}, {"Joyce v. Wilkenning": ["2481692", 1]}, {"Bryan v. Sanderson": ["2489647", 1]}], "Utah": [7, {"Kahn v. Old Telegraph Mining Co.": ["8887705", 1]}, {"Cast v. Cast": ["8871900", 1]}, {"McGee v. Connor": ["8871846", 1]}, {"Victor Sewing Machine Co. v. Crockwell": ["8888647", 1]}, {"People v. Green": ["8871606", 1]}, {"Walker v. Popper": ["8887888", 1]}, {"Bachman v. Smith": ["8872383", 1]}], "Wash.": [1, {"Stevens v. Baker": ["784324", 1]}], "Idaho": [1, {"People v. Walter": ["8858574", 1]}], "Haw.": [1, {"Minister of Interior v. Glover": ["1540308", 1]}]}