{"Mass.": [6638, {"Hill v. City of Boston": ["2134634", 8]}, {"Grace v. Adams": ["2141770", 7]}, {"Commonwealth v. Coe": ["718036", 7]}, {"Woodman v. Metropolitan Railroad": ["778425", 7]}, {"Milliken v. Pratt": ["730867", 7]}, {"Stone v. Hackett": ["2086067", 7]}, {"Rooney v. Sewall & Day Cordage Co.": ["797244", 7]}, {"Sullivan v. India Manufacturing Co.": ["741045", 7]}, {"Ferren v. Old Colony Railroad": ["772441", 7]}, {"Commonwealth v. Alger": ["1967525", 6]}], "N.Y.": [24166, {"In re Jacobs": ["558002", 21]}, {"Stuart v. Palmer": ["534666", 21]}, {"Lawrence v. Fox": ["2022913", 20]}, {"Smith v. People": ["509414", 17]}, {"Barrett v. Third Avenue Railroad": ["2049791", 17]}, {"Pantzar v. Tilly Foster Iron Mining Co.": ["2196949", 16]}, {"People ex rel. Union Trust Co. v. Coleman": ["2237642", 16]}, {"Hoormann v. Climax Cycle Co.": ["2288169", 16]}, {"Heaney v. Long Island Railroad": ["2219733", 15]}, {"Searles v. Manhattan Railway Co.": ["2201424", 15]}], "Pa.": [10739, {"Schum v. Pennsylvania Railroad": ["8856037", 15]}, {"Davidson v. Lake Shore & Michigan Southern Railway Co.": ["985571", 13]}, {"Pittsburgh Southern Railway Co. v. Taylor": ["452206", 12]}, {"Ely v. Pittsburgh, Cincinnati, Chicago & St. Louis Railway": ["848225", 12]}, {"Thomas & Sons v. Loose, Seaman & Co.": ["549986", 12]}, {"Goshorn v. Smith": ["491011", 11]}, {"Phillips v. Meily": ["455579", 11]}, {"Reichenbach v. Ruddach": ["565723", 11]}, {"Hoag v. Lake Shore & Michigan Southern Railroad": ["440494", 10]}, {"Titus v. Bradford etc. R.": ["820016", 10]}], "Md.": [1346, {"Mayor of Baltimore v. Radecke": ["1823058", 8]}, {"Swift v. Smith, Dixon & Co.": ["1808705", 5]}, {"Winchester v. Baltimore & Susquehanna R. R.": ["1695154", 4]}, {"Crawford v. Rohrer": ["1038934", 4]}, {"Higgins v. Carlton": ["1764159", 4]}, {"Nelson v. Hagerstown Bank": ["1762327", 4]}, {"Mayhew v. Boyd": ["1696635", 3]}, {"Citizens\u2019 Fire Insurance, Security & Land Co. v. Doll": ["1023776", 3]}, {"Tome v. Parkersburg Branch Railroad": ["1842562", 3]}, {"State v. Dalrymple": ["1813857", 3]}], "Wis.": [2911, {"State ex rel. Kennedy v. Brunst": ["11285160", 9]}, {"Kellogg v. Chicago & Northwestern Railway Co.": ["11284697", 7]}, {"Wheeler v. Town of Westport": ["11285349", 7]}, {"Atkinson v. Goodrich Transportation Co.": ["11283064", 6]}, {"Prutsman v. Baker": ["11286071", 6]}, {"McLeod v. Evans": ["11283576", 6]}, {"Craker v. Chicago & Northwestern Railway Co.": ["8708521", 6]}, {"Kelley v. Town of Fond du Lac": ["8707132", 6]}, {"Ford v. Hill": ["8703047", 6]}, {"Brown v. Chicago, Milwaukee & St. Paul Railway Co.": ["11284280", 5]}], "Miss.": [967, {"Shelby v. Alcorn": ["8837598", 6]}, {"Pollard v. State": ["1669984", 4]}, {"Schumpert v. Dillard, Pinson & Co.": ["1665773", 4]}, {"Payne v. State": ["1796569", 4]}, {"New Orleans, St. Louis & Chicago Railroad v. Burke": ["1670064", 3]}, {"Mills v. New Orleans Seed Co.": ["371951", 3]}, {"Union Mortgage, Banking & Trust Co. v. Peters & Trezevant": ["8838322", 3]}, {"Murphy v. Red": ["8837351", 3]}, {"Swann v. Buck": ["9512202", 3]}, {"Simmons v. State": ["1796588", 3]}], "Kan.": [1575, {"State ex rel. Johnson v. Hitchcock": ["63915", 5]}, {"First National Bank v. Peck": ["595648", 5]}, {"Missouri Pacific Railway Co. v. Sharitt": ["1220903", 5]}, {"Howell v. A. Manglesdorf & Co.": ["8859697", 4]}, {"Ryus v. Gruble": ["1069996", 4]}, {"Board of Commissioners v. Shoemaker": ["611140", 4]}, {"Myers v. Board of Education": ["1146016", 4]}, {"Burhans v. Hutcheson": ["8866935", 4]}, {"Long v. Murphy": ["611130", 4]}, {"Hoisington v. Brakey": ["1070028", 4]}], "Ohio": [2697, {"Goodin v. Cincinnati & Whitewater Canal Co.": ["43714", 10]}, {"Hixson v. Burson": ["50818", 10]}, {"State v. Standard Oil Co.": ["8841045", 8]}, {"State ex rel. Attorney-General v. Hawkins": ["923283", 8]}, {"Little Miami Railroad v. Commissioners of Greene County": ["899895", 8]}, {"State v. Commissioners": ["8841160", 8]}, {"Lehman v. McBride": ["524646", 7]}, {"Railroad Co. v. Morey": ["928344", 7]}, {"Sinks v. Reese": ["882934", 6]}, {"State ex rel. City of Columbus v. Mitchell": ["899988", 6]}], "La.": [299, {"Childs v. New Orleans City Railroad": ["322653", 3]}, {"Phillips v. Louisiana Equitable Life Insurance": ["5238913", 3]}, {"Henderson v. Ship Maid of Orleans": ["573236", 3]}, {"Ware F. M. C. v. Barataria & Lafourche Canal Co.": ["645460", 2]}, {"State ex rel. Phelps v. Judge of the Civil District Court": ["2537792", 2]}, {"Succession of A. Constant Hearing": ["5241593", 2]}, {"Plicque & Lebeau v. Perret": ["8749102", 2]}, {"State v. Molisse": ["2606377", 2]}, {"Citizens\u2019 Bank v. Maureau": ["2602035", 2]}, {"Henderson v. A. Meyers & Bro.": ["289511", 2]}], "Mo.": [12257, {"Huhn v. Missouri Pacific Railway Co.": ["1024288", 17]}, {"O\u2019Mellia v. Kansas City": ["989046", 16]}, {"Waldhier v. Hannibal & St. Joseph Railroad": ["451569", 16]}, {"State v. Paxton": ["469892", 12]}, {"Tomlinson v. Ellison": ["420474", 11]}, {"McCullough v. Ph\u0153nix Insurance": ["8843911", 11]}, {"Spohn v. Missouri Pacific Railway Co.": ["436392", 10]}, {"Pomeroy v. Benton": ["8852870", 9]}, {"Scovill v. Glasner": ["942001", 9]}, {"Powell v. Missouri Pacific Railway Co.": ["443883", 9]}], "Neb.": [2660, {"Sample v. Hale": ["4430708", 7]}, {"Andres v. Kridler": ["2643170", 7]}, {"Chicago, Burlington & Quincy Railroad v. Bell": ["4449781", 6]}, {"Gran v. Houston": ["4451251", 6]}, {"State ex rel. Churchill v. Bemis": ["4450593", 6]}, {"State ex rel. Farmers Mutual Insurance v. Moore": ["8551161", 6]}, {"Romberg v. Fokken": ["2643022", 6]}, {"Camp v. Pollock": ["4451226", 6]}, {"Anheuser-Busch Brewing Ass'n v. Peterson": ["4444012", 6]}, {"Staley v. Housel": ["4433193", 6]}], "Ark.": [1184, {"L. R. & F. S. R. R. v. Payne": ["8726426", 4]}, {"Fordyce v. Jackson": ["1326165", 4]}, {"State v. Morrill": ["8725284", 4]}, {"Worthen v. Badgett": ["1877174", 4]}, {"Collins v. Mack": ["1879334", 4]}, {"Chrisman v. Carney": ["8723800", 4]}, {"Radcliffe v. Scruggs": ["1890471", 4]}, {"Railway Co. v. Cravens": ["1324670", 4]}, {"Ex parte McMeechen": ["8727693", 3]}, {"Files v. Fuller": ["1893399", 3]}], "Ill.": [8044, {"Pullman Palace Car Co. v. Laack": ["3080364", 9]}, {"Law v. People ex rel. Huck": ["5340642", 8]}, {"Bruce v. Schuyler": ["2561675", 8]}, {"City of Springfield v. Edwards": ["2652149", 8]}, {"Peirce v. Walters": ["5503723", 8]}, {"Rigney v. City of Chicago": ["2811284", 7]}, {"Spies v. People": ["5390344", 7]}, {"Toledo, Wabash & Western Railway Co. v. Beggs": ["2776330", 7]}, {"Lake Shore & Michigan Southern Railway Co. v. Richards": ["835361", 7]}, {"McKinley v. Watkins": ["2583352", 7]}], "Cal.": [5100, {"Ex parte Maier": ["2340087", 7]}, {"Lux v. Haggin": ["2312996", 6]}, {"People v. Goldenson": ["2323715", 6]}, {"Miners\u2019 Ditch Co. v. Zellerbach": ["2224990", 6]}, {"Jolley v. Foltz": ["2284584", 6]}, {"People v. Gold Run Ditch & Mining Co.": ["2249783", 6]}, {"Carpenter v. Bailey": ["1920609", 6]}, {"Shea v. Potrero & Bay View Railroad": ["2316165", 5]}, {"Lathrop v. Bampton": ["2222646", 5]}, {"Davis v. Davis": ["2203978", 5]}], "Mich.": [3143, {"People ex rel. Drake v. Mahaney": ["1949681", 6]}, {"Lake Shore & Michigan Southern Railroad v. Miller": ["1311036", 6]}, {"Crawford v. Edwards": ["1346614", 6]}, {"Bank of Montreal v. J. E. Potts Salt & Lumber Co.": ["1371437", 6]}, {"Knapp v. Swaney": ["1430061", 6]}, {"People ex rel. Le Roy v. Hurlbut": ["1938283", 5]}, {"People ex rel. Board of Park Commissioners v. Common Council": ["1953446", 5]}, {"Redmond v. Delta Lumber Co.": ["1530934", 5]}, {"Peoria Marine & Fire Insurance v. Hall": ["1950666", 5]}, {"Davis v. Detroit & Milwaukee Rail Road": ["1939969", 5]}], "Iowa": [3074, {"Buell v. Buckingham & Co.": ["2291585", 7]}, {"State v. Cater": ["2099849", 7]}, {"Grant v. City of Davenport": ["2301337", 6]}, {"Osgood & Moss v. King": ["2309190", 6]}, {"Bruse v. Nelson": ["109205", 6]}, {"Van Patten v. Burr": ["2322165", 6]}, {"Clark v. City of Des Moines": ["2290527", 5]}, {"McPherson v. Foster Bros.": ["2310611", 5]}, {"Independent District v. King": ["2070649", 5]}, {"Parkhill v. Town of Brighton": ["4371009", 5]}], "N.J.": [1166, {"Wilkinson v. Bauerle": ["785040", 6]}, {"Stratton v. Allen": ["514221", 5]}, {"Barnes v. Trenton Gas Light Co.": ["536579", 4]}, {"Graham Button Co. v. Spielmann": ["99836", 4]}, {"Besson v. Eveland": ["534834", 4]}, {"Hackensack Water Co. v. De Kay": ["796289", 4]}, {"Halsey v. Rapid Transit Street Railway Co.": ["92976", 4]}, {"Delaware, Lackawanna & Western Railroad v. Salmon": ["351505", 4]}, {"Daggers v. Van Dyck": ["775722", 3]}, {"Receivers of the New Jersey Midland Railway Co. v. Wortendyke": ["536584", 3]}], "N.H.": [1042, {"Eaton v. B. C. & M. R. R.": ["11251573", 6]}, {"King v. Chase": ["4401370", 5]}, {"Winship v. Enfield": ["4546444", 4]}, {"Fowler v. Brooks": ["467601", 4]}, {"In re Sturoc": ["1050293", 4]}, {"Horn v. Cole": ["11250617", 4]}, {"Hardy v. Merrill": ["1803605", 4]}, {"Cook v. Brown": ["4530571", 4]}, {"Sleeper v. N. H. F. Insurance": ["1803638", 4]}, {"Metcalf v. Gilmore": ["4470360", 4]}], "Minn.": [2662, {"Hospes v. Northwestern Manuf\u2019g & Car Co.": ["741421", 10]}, {"Herrick v. Minneapolis & St. Louis Railway Co.": ["749055", 7]}, {"Emmert v. Thompson": ["8876399", 6]}, {"Nichols v. Walter": ["8877377", 6]}, {"Lindvall v. Woods": ["565534", 6]}, {"Cook v. St. Paul, Minneapolis & Manitoba Railway Co.": ["8876316", 6]}, {"State ex rel. Powell v. State Medical Examining Board": ["756708", 6]}, {"Wilson v. Minnesota Farmers\u2019 Mutual Fire Insurance": ["563723", 6]}, {"First National Bank v. Gustin Minerva Consolidated Mining Co.": ["750772", 6]}, {"Farmers\u2019 Loan & Trust Co. v. Minneapolis Engine & Machine Works": ["8877754", 6]}], "Tex.": [3326, {"Murchison v. White": ["2182783", 7]}, {"Wofford v. McKinna": ["2114478", 6]}, {"Tuttle v. Turner, Wilson & Co.": ["2102712", 5]}, {"Cannon v. Cannon": ["2202597", 5]}, {"Seale. v. Gulf, Colorado & Santa Fe R\u2019y Co.": ["2204519", 5]}, {"Texas Pacific Railway Co. v. Johnson": ["2225340", 4]}, {"Continental National Bank v. Weems": ["2196068", 4]}, {"Wright v. Adams": ["2160518", 4]}, {"Rowell v. Western Union Telegraph Co.": ["2184989", 4]}, {"Price v. Supreme Lodge Knights of Honor": ["2198803", 4]}], "Ga.": [1675, {"Keener v. State": ["587117", 5]}, {"Berry v. State": ["574956", 5]}, {"Head v. Georgia Pacific Railway Co.": ["63828", 5]}, {"Mayor of Macon v. Franklin": ["589467", 4]}, {"Henderson v. Walker": ["575521", 3]}, {"Campbell & Jones v. Murray": ["21858", 3]}, {"Brown v. State": ["584096", 3]}, {"Dumas v. State": ["24375", 3]}, {"Pattison v. Albany Building & Loan Ass'n": ["24404", 3]}, {"Ingram v. Little": ["577654", 3]}], "N.C.": [1926, {"Wittkowsky v. Wasson": ["11278636", 9]}, {"King v. Hunter": ["1955480", 6]}, {"Hoke v. Henderson": ["11275271", 5]}, {"State v. Riley": ["8653775", 5]}, {"State v. Moore": ["8652134", 4]}, {"State v. Gooch": ["8652755", 4]}, {"Haynes v. Kaleigh Gas Co.": ["8649694", 4]}, {"Meroney v. Atlanta Building & Loan Ass'n": ["8655827", 4]}, {"State v. Shule": ["1972576", 4]}, {"Parker v. Beasley": ["8654136", 4]}], "Ind.": [6064, {"Rogers v. Eich": ["1571959", 11]}, {"De Hart v. Board of Commissioners": ["1590433", 10]}, {"Board of Commissioners v. Bonebrake": ["1572062", 10]}, {"Manley v. Felty": ["1572016", 10]}, {"Deal v. State": ["1631460", 9]}, {"Board of Commissioners v. Allman": ["1610284", 8]}, {"Epps v. State": ["1358660", 8]}, {"Union School Township v. National Bank": ["1358742", 8]}, {"Cincinnati, Indianapolis, St. Louis & Chicago Railway Co. v. Grames": ["1409993", 8]}, {"Kelso v. Kelso": ["2405172", 8]}], "Conn.": [1200, {"State v. Carroll": ["759975", 6]}, {"Hayden v. Smithville Manufacturing Co.": ["530645", 5]}, {"Zaleski v. Clark": ["750385", 5]}, {"Catlin v. Eagle Bank of New-Haven": ["6754566", 5]}, {"Bissell v. Davison": ["806198", 5]}, {"Wilson v. Willimantic Linen Co.": ["506211", 4]}, {"Morris v. Platt": ["535499", 4]}, {"Welch v. Seymour": ["527710", 4]}, {"Johnson v. Lewis": ["6754374", 4]}, {"City of Bridgeport v. Housatonuc Railroad": ["6754688", 4]}], "Fla.": [364, {"Jacksonville, Tampa & Key West Railway Co. v. Peninsular Land, Transportation & Manufacturing Co.": ["1142541", 5]}, {"Watrous v. Morrison": ["1087273", 4]}, {"Baker v. State": ["1140845", 3]}, {"State ex rel. Bloxham v. Gibbs": ["1159163", 3]}, {"Levy v. Cox": ["1137393", 3]}, {"Wilkinson v. Pensacola & Atlantic Railroad": ["1080191", 3]}, {"Waterman v. Higgins": ["1134720", 3]}, {"Ballard v. Lippman Bros.": ["8849969", 3]}, {"Storrs v. Storrs": ["1120563", 3]}, {"Dixon v. State": ["1159172", 2]}], "Vt.": [1221, {"Thorpe v. Rutland & Burlington Railroad": ["740272", 7]}, {"Porter v. Bank of Rutland": ["4422454", 4]}, {"Hyde v. Cooper": ["4428905", 4]}, {"Hemmenway v. Corey": ["4420759", 4]}, {"Allen v. Drew": ["11267102", 3]}, {"Herrick v. Estate of Belknap": ["740336", 3]}, {"Childs v. Millville Mutual M. & F. Ins.": ["754008", 3]}, {"Stimpson v. Putnam": ["8544669", 3]}, {"State v. Ward": ["764158", 3]}, {"Raycroft v. Tayntor": ["4456781", 3]}], "Tenn.": [657, {"Wally\u2019s Heirs v. Kennedy": ["11267339", 5]}, {"Insurance Co. v. Bennett": ["11264090", 4]}, {"Stephens v. State": ["11266674", 4]}, {"Street Railroad Co. v. Morrow": ["8538219", 3]}, {"Sutton v. State": ["8536975", 3]}, {"Miller v. Insurance Company": ["8537890", 3]}, {"Fogarty v. Stack": ["8538386", 3]}, {"Railway Co. v. Wynn": ["11264121", 3]}, {"Tally v. Ayres": ["8542585", 3]}, {"Nashville Trust Co. v. Bank": ["8538000", 3]}], "Ala.": [3451, {"Montgomery v. State ex rel. Enslen": ["3338884", 6]}, {"Supreme Commandery of the Knights of the Golden Rule v. Ainsworth": ["11255477", 6]}, {"Western Union Telegraph Co. v. Henderson": ["3277872", 5]}, {"State v. Rogers": ["3337222", 5]}, {"Frenkel v. Hudson": ["3323177", 5]}, {"Griffith v. State": ["5574489", 5]}, {"Spicer v. State": ["3311754", 5]}, {"Barnhill v. Teague": ["8492676", 5]}, {"Mayor of Mobile v. Stonewall Insurance": ["3344970", 4]}, {"Marshall v. Betner": ["3133337", 4]}], "Colo.": [590, {"Trimble v. People ex rel. Phelps": ["2511382", 5]}, {"Denver, South Park & Pacific Railway Co. v. Woodward": ["5286479", 4]}, {"Brooks v. Bradford": ["4473349", 4]}, {"Nesbit v. People": ["2512075", 3]}, {"Great West Min. Co. v. Woodmas of Alston Min. Co.": ["2582536", 3]}, {"Cooper v. People ex rel. Wyatt": ["2505201", 3]}, {"Hall v. Linn": ["2579693", 3]}, {"Sieber v. Frink": ["2554301", 3]}, {"Utley v. Clark-Gardner Lode Mining Co.": ["5286432", 3]}, {"People v. Osborne": ["2554591", 3]}], "Me.": [1628, {"Franklin Bank v. Cooper": ["634596", 8]}, {"Long v. Woodman": ["684331", 5]}, {"Knight v. Portland, Saco & Portsmouth Railroad": ["667009", 5]}, {"Fairfield Savings Bank v. Chase": ["8844442", 5]}, {"Berry v. Cutts": ["671423", 5]}, {"Inhabitants of Veazie v. Penobscot Railroad": ["621822", 4]}, {"State v. Noyes": ["349132", 4]}, {"Pillsbury v. Moore": ["682684", 4]}, {"Philbrook v. Delano": ["8847148", 4]}, {"Lake v. Milliken": ["630326", 4]}], "Nev.": [287, {"State ex rel. Nourse v. Clarke": ["4648583", 4]}, {"State v. Ah Chew": ["11273528", 4]}, {"Golden Fleece G. & S. M. Co. v. Cable Consolidated G. & S. M. Co.": ["4651936", 3]}, {"Hoole v. Kinkead": ["11274054", 3]}, {"Phillips v. Welch": ["4620761", 3]}, {"State ex rel. Curtis v. McCullough": ["4648417", 3]}, {"State v. Virginia & Truckee Railroad": ["4636502", 2]}, {"Proprietors of the Mexican Mill v. Yellow Jacket Silver Mining Co.": ["8577121", 2]}, {"Doak v. Brubaker": ["8847545", 2]}, {"State v. Rhoades": ["11273845", 2]}], "Idaho": [151, {"Bannock County v. Bunting": ["5617025", 4]}, {"Hampton v. Commissioners of Logan County": ["5617121", 4]}, {"Black v. City of Lewiston": ["8858285", 2]}, {"Baker v. Scott": ["5619175", 2]}, {"Bellevue Water Co. v. Stockslager": ["5616965", 2]}, {"Wright v. Kelley": ["5617860", 2]}, {"Cohn v. Kingsley": ["8586450", 2]}, {"McCarty v. Boise City Canal Co.": ["8858023", 2]}, {"Winters v. Swift": ["8857040", 2]}, {"Ada County v. Gess": ["5619391", 2]}], "S.C.": [1231, {"Norris v. Clinkscales": ["4404667", 8]}, {"Trumbo v. Finley": ["4378668", 5]}, {"Hart v. Bates": ["363285", 4]}, {"Carter v. Columbia & Greenville R. R.": ["4380519", 4]}, {"Clayton v. Mitchell": ["4391742", 4]}, {"Kennerty v. Etiwan Phosphate Co.": ["2343648", 3]}, {"Salinas & Son v. Ellis": ["4386073", 3]}, {"Darwin v. Charlotte, Columbia & Augusta R. R.": ["4383616", 3]}, {"Woolfolk v. Graniteville Manufacturing Co.": ["4382541", 3]}, {"Witte v. Weinberg": ["4397639", 3]}], "Ky.": [999, {"Basye v. Adams": ["1311694", 5]}, {"Bodine\u2019s Adm\u2019rs v. Arthur": ["4405657", 5]}, {"Jordan\u2019s Adm\u2019r v. Cincinnati, New Orleans & Texas Pacific Railroad": ["2347545", 4]}, {"Chapman v. Western Union Telegraph Co.": ["2349397", 4]}, {"Hutchcraft's Ex'r v. Travelers' Insurance": ["4402178", 4]}, {"Louisville & Portland Canal Co. v. Murphy": ["4387730", 4]}, {"Fecheimer Bros. & Co. v. City of Louisville": ["1319151", 4]}, {"Henderson's Adm'r v. Ky. Cent. R. R.": ["1320682", 3]}, {"Bank of America v. McNeil": ["4389479", 3]}, {"Kleeman & Co. v. Collins": ["4386284", 3]}], "Va.": [789, {"Johnson\u2019s Adm\u2019r v. Chesapeake & Ohio Railway Co.": ["2336269", 7]}, {"Norfolk & Western R. v. Ampey": ["1870707", 7]}, {"Planters Bank of Farmville v. Whittle": ["4390459", 5]}, {"Burch v. Hardwicke": ["4431825", 4]}, {"Norfolk & Western Railroad v. H. I. Shott": ["2338404", 4]}, {"Seaboard & Roanoke Railroad v. Joyner\u2019s Adm\u2019r": ["2338413", 4]}, {"Max Meadows Land & Improvement Co. v. Brady": ["2338459", 4]}, {"Union Central Life Ins. v. Pollard": ["1868905", 3]}, {"Hodge\u2019s Ex\u2019or v. First Nat. Bank": ["4435008", 3]}, {"Norfolk & Western Railroad v. Nuckol\u2019s Adm\u2019r": ["2336271", 3]}], "R.I.": [348, {"Hagan v. Providence & Worcester R. R.": ["8518770", 4]}, {"State v. Smith": ["5138929", 4]}, {"Sutcliffe v. Atlantic Mills": ["729810", 3]}, {"Clark v. Allen": ["1328989", 3]}, {"Taggart v. Newport Street Railway Co.": ["4823535", 3]}, {"Peck v. Peck": ["11269421", 3]}, {"Wixon v. City of Newport": ["729532", 3]}, {"Cleveland v. Tripp": ["729572", 2]}, {"Smith v. Old Colony & Newport Railroad": ["725305", 2]}, {"Bennett v. Fifield": ["729558", 2]}], "W. Va.": [630, {"Stout v. Philippi Manufacturing & Mercantile Co.": ["12165677", 4]}, {"Smith v. Yoke": ["8640598", 4]}, {"State ex rel. Robinson v. Brookover": ["8639167", 4]}, {"State v. Goodwill": ["8639811", 3]}, {"West Virginia Transportation Co. v. Ohio River Pipe Line Co.": ["8640845", 3]}, {"Darby & Co. v. Gilligan": ["8639915", 3]}, {"Washington v. B. & O. R. R.": ["8640814", 3]}, {"State v. Frew & Hart": ["8640590", 3]}, {"Roberts v. Coleman": ["8639272", 3]}, {"State v. McClaugherty": ["8639932", 3]}], "Wash.": [451, {"Cloud v. Town of Sumas": ["5058812", 4]}, {"Roth v. Union Depot Co.": ["299372", 4]}, {"City of New Whatcom v. Bellingham Bay Improvement Co.": ["5103690", 4]}, {"Winston v. City of Spokane": ["782050", 3]}, {"Eidemiller v. City of Tacoma": ["8531227", 3]}, {"Hinchman v. Point Defiance Railway Co.": ["8531183", 3]}, {"Jolliefe v. Brown": ["8530800", 3]}, {"Turner v. Bailey": ["782090", 3]}, {"Guley v. Northwestern Coal & Transportation Co.": ["5085086", 3]}, {"Olympia Water Works v. Thurston County": ["8531039", 3]}], "S.D.": [223, {"Barnard & Leas Manuf\u2019g Co. v. Galloway": ["4468939", 5]}, {"Sandmeyer v. Dakota Fire & Marine Insurance": ["4512298", 4]}, {"State v. Chicago, Milwaukee & St. Paul Railway Co.": ["4467400", 4]}, {"Wright v. Lee": ["4510307", 3]}, {"Hegeler v. Comstock": ["919951", 3]}, {"Humpfner v. D. M. Osborne & Co.": ["4511882", 3]}, {"Hill v. Alliance Building Co.": ["17106", 3]}, {"Vallier v. Brakke": ["20040", 3]}, {"Gade v. Collins": ["11254309", 3]}, {"Hawkins v. Hubbard": ["4509277", 2]}], "Dakota Territory": [62, {"Caledonia Gold Mining Co. v. Noonan": ["8586644", 3]}, {"Lloyd v. Powers": ["2602898", 3]}, {"Territory of Dakota ex rel. McMahon v. O\u2019Connor": ["8586924", 3]}, {"Everett v. Buchanan": ["8586725", 3]}, {"Elliot v. Chicago, M. & St. P. Ry. Co.": ["8587001", 3]}, {"Straw v. Jenks": ["2606178", 2]}, {"Myrick v. Bill": ["8586727", 2]}, {"Opening of Gold Street v. Newton": ["8586521", 2]}, {"Feldenheimer v. Tressel": ["2606160", 2]}, {"Jones v. Matthieson": ["8586905", 2]}], "N.D.": [130, {"O\u2019Neil v. Tyler": ["5290209", 5]}, {"Power v. Larabee": ["5285642", 4]}, {"Power v. Bowdle": ["5291184", 3]}, {"Cutter v. Pollock": ["194645", 3]}, {"Hostetter v. Brooks Elevator Co.": ["194649", 3]}, {"Lavin v. Bradley": ["2558261", 2]}, {"Union National Bank v. Oium": ["5290505", 2]}, {"First National Bank v. Laughlin": ["194616", 2]}, {"Anderson v. First Nat. Bank": ["5292761", 2]}, {"State v. Markuson": ["5292404", 2]}], "Mont.": [233, {"Stackpole v. Hallahan": ["4374248", 3]}, {"Hotchkiss v. Marion": ["2279019", 3]}, {"State ex rel. Woody v. Rotwitt": ["8588090", 3]}, {"State ex rel. Northwestern National Bank v. Dickerman": ["4373414", 3]}, {"State v. Biesman": ["2279020", 2]}, {"Davenport v. Kleinschmidt": ["1964847", 2]}, {"Diamond v. Northern Pac. R. Co.": ["1964842", 2]}, {"Power v. First Nat. Bank": ["1964880", 2]}, {"Waterbury v. Board of Commissioners": ["2280950", 2]}, {"Bank of Commerce v. Fuqua": ["2277722", 2]}], "Or.": [568, {"Wist v. Grand Lodge A. O. U. W.": ["2274347", 4]}, {"Dahms v. Sears": ["2284426", 4]}, {"Inman v. Sprague": ["2261201", 4]}, {"Lewis v. Lewis": ["2295351", 3]}, {"Northern Counties Trust v. Sears": ["2261227", 3]}, {"Pearce v. Buell": ["2274312", 3]}, {"Ferchen v. Arndt": ["2267810", 3]}, {"Bradtfeldt v. Cooke": ["2266069", 3]}, {"Frink v. Thomas": ["2276194", 3]}, {"Simmons v. Winters": ["8660494", 3]}], "Ariz.": [18, {"Rush v. French": ["1969437", 2]}, {"King v. Hawkins": ["2881835", 1]}, {"Territory of Arizona v. Connell": ["2877467", 1]}, {"Clough v. Wing": ["2877959", 1]}, {"Territory of Arizona v. Youree": ["5379433", 1]}, {"Johnston v. Letson": ["5379690", 1]}, {"Barter v. County of Pima": ["2881635", 1]}, {"Territory of Arizona v. Meyer": ["5378938", 1]}, {"Oury v. Goodwin": ["5378719", 1]}, {"Arizona Lumber & Timber Co. v. Mooney": ["2887100", 1]}], "Utah": [231, {"White v. Pease": ["8874323", 6]}, {"Saunders v. Southern Pacific Co.": ["8873434", 4]}, {"Chapman v. Southern Pacific Co.": ["8873849", 3]}, {"Clark v. Fisk": ["8871672", 3]}, {"Woods v. Southern Pacific Co.": ["8871789", 3]}, {"Drummond v. Southern Pacific Co.": ["8873963", 3]}, {"North Point Consolidated Irrigation Co. v. Utah & Salt Lake Canal Co.": ["8874699", 3]}, {"State v. Bates": ["8874861", 3]}, {"Eastman v. Gurrey": ["8874703", 3]}, {"W. P. Noble Mercantile Co. v. Mount Pleasant Equitable Co-operative Institution": ["8873906", 3]}], "Okla.": [74, {"Woodruff v. Wallace": ["8878667", 8]}, {"McMechan v. Christy": ["8878505", 3]}, {"City of Oklahoma City v. Hill": ["8879290", 3]}, {"Hoffman v. County Commissioners": ["8878633", 3]}, {"National Bank v. Earl": ["8879081", 3]}, {"Sproat v. Durland": ["8877755", 3]}, {"Mulhall v. Mulhall": ["8878544", 2]}, {"Pittman v. City of El Reno": ["8879484", 2]}, {"Farris v. Henderson": ["62675", 2]}, {"E. S. Jaffray & Co. v. Wolf & Son": ["62762", 2]}], "Del.": [57, {"Union Church of Africans v. Sanders": ["1861508", 3]}, {"Satterthwait v. Marshall": ["471205", 2]}, {"Beeson v. Elliott": ["457843", 1]}, {"Knight v. Ferris": ["72450", 1]}, {"Murphy v. Mayor & Council": ["72500", 1]}, {"Stewart v. Philadelphia, W. & B. R.": ["64754", 1]}, {"Quinn v. Johnson Forge Co.": ["66497", 1]}, {"Vandergrift v. Hollis": ["72496", 1]}, {"Beeber v. Walton": ["63045", 1]}, {"Frankel v. Satterfield": ["66491", 1]}], "D.C.": [168, {"Hisey v. Peters": ["1328042", 5]}, {"Durham v. Seymour": ["1328030", 3]}, {"United States v. Guiteau": ["8482169", 3]}, {"United States ex rel. Brightwood Railway Co. v. O\u2019Neal": ["1324124", 3]}, {"Barbour v. Moore": ["2626328", 3]}, {"Rathbone v. Hamilton": ["2626503", 3]}, {"Hendley v. Clark": ["6097578", 3]}, {"Beckett v. Tyler": ["2491962", 2]}, {"Clark v. Krause": ["2492252", 2]}, {"Johnson v. Van Wyck": ["2625992", 2]}], "Wyo.": [24, {"State ex rel. Holcombe v. Burdick": ["8516010", 1]}, {"Graham v. Blinn": ["8516257", 1]}, {"State ex rel. Henderson v. Burdick": ["8516007", 1]}, {"Slaymaker v. Phillips": ["8516296", 1]}, {"Smith v. Harrington": ["8516145", 1]}, {"Fields v. Territory of Wyoming": ["5271856", 1]}, {"Fillmore v. Union Pacific Railroad": ["8516130", 1]}, {"State v. Foster": ["8516141", 1]}, {"Cowhick v. Shingle": ["8516105", 1]}, {"North Platte Milling & Elevator Co. v. Price": ["8516016", 1]}], "N.M.": [23, {"Cordova Et Al. v. Korte": ["4657606", 2]}, {"Marshall Field & Co. v. M. Romero & Co.": ["4659584", 2]}, {"Witt v. Cuenod": ["2382237", 1]}, {"Bull v. Southwick": ["3284988", 1]}, {"Finane v. Las Vegas Hotel & Imp. Co.": ["3283396", 1]}, {"Territory of New Mexico v. Kelly": ["3285123", 1]}, {"Padilla v. Territory of New Mexico": ["4665955", 1]}, {"Waldo v. Beckwith": ["8300659", 1]}, {"Atchison, Topeka & Santa Fe Railroad v. Martin": ["4658045", 1]}, {"Barnett v. Barnett": ["2381756", 1]}], "Haw.": [42, {"The King ex rel. Bradley v. Thurston": ["1530513", 2]}, {"Castle v. Kapena": ["1528841", 1]}, {"Thurston v. Allen": ["1532536", 1]}, {"Harris v. Judd": ["1540290", 1]}, {"In re the Estate of His Majesty Kamehameha IV": ["1538382", 1]}, {"Kapena v. Kaleleonalani": ["6111208", 1]}, {"Mokuai v. Kapuniai": ["6099164", 1]}, {"The Queen v. San Tana": ["1536639", 1]}, {"Ohera v. Ackerman": ["1536721", 1]}, {"Vierra v. Ropert": ["6756623", 1]}]}