{"Mass.": [7717, {"Commonwealth v. Soares": ["334144", 25]}, {"Commonwealth v. Freeman": ["304943", 24]}, {"Commonwealth v. Latimore": ["337417", 18]}, {"Fortune v. National Cash Register Co.": ["323873", 15]}, {"Commonwealth v. Saferian": ["314554", 13]}, {"Commonwealth v. Henson": ["385134", 13]}, {"Commonwealth v. Bradshaw": ["900792", 13]}, {"Ferriter v. Daniel O\u2019Connell\u2019s Sons, Inc.": ["816156", 13]}, {"Superintendent of Belchertown State School v. Saikewicz": ["324210", 12]}, {"Irwin v. Town of Ware": ["3875139", 12]}], "N.Y.": [32827, {"People v. Contes": ["4393163", 185]}, {"People v. Gonzalez": ["4371492", 181]}, {"People v. Malizia": ["2348514", 122]}, {"People v. Crimmins": ["2317079", 105]}, {"People v. Harris": ["2345681", 99]}, {"People v. Suitte": ["5619091", 96]}, {"People v. Pellegrino": ["4393508", 82]}, {"Pell v. Board of Education": ["2311764", 81]}, {"Zuckerman v. City of New York": ["4373856", 68]}, {"In re Aho": ["2323797", 60]}], "Miss.": [4544, {"Neal v. State": ["7623482", 24]}, {"Billiot v. State": ["7616962", 20]}, {"Paymaster Oil Mill Co. v. Mitchell": ["9641934", 17]}, {"Standard Life Insurance Co. of Indiana v. Veal": ["9701598", 15]}, {"Stanton & Associates, Inc. v. Bryant Construction Co.": ["7621385", 15]}, {"Hall v. Hilbun": ["7623545", 14]}, {"City of Jackson v. Locklar": ["9525365", 14]}, {"Cabello v. State": ["7602249", 13]}, {"Luckett v. Mississippi Wood Inc.": ["7592263", 13]}, {"Johnson v. State": ["7623911", 13]}], "Mo.": [12700, {"Murphy v. Carron": ["10120440", 164]}, {"Schranz v. Director of Revenue": ["9989665", 67]}, {"Gustafson v. Benda": ["9925136", 31]}, {"Collins v. Director of Revenue": ["9964254", 26]}, {"State v. Newlon": ["9975174", 23]}, {"State v. Taylor": ["9934143", 22]}, {"State v. Smith": ["9940895", 22]}, {"Hofmann v. Hoffmann": ["9952921", 21]}, {"State v. Johns": ["9932805", 20]}, {"Keener v. Dayton Electric Manufacturing Co.": ["10144917", 18]}], "Me.": [1801, {"State v. Barry": ["7920105", 33]}, {"State v. True": ["7969806", 14]}, {"Culbert v. Sampson\u2019s Supermarkets Inc.": ["7964755", 9]}, {"State v. Freeman": ["7920673", 7]}, {"Adams v. Buffalo Forge Co.": ["7998051", 6]}, {"Townsend v. Maine Bureau of Public Safety": ["8047235", 6]}, {"Concord General Mutual Insurance v. Patrons-Oxford Mutual Insurance": ["11367624", 6]}, {"Harmon v. Emerson": ["7994230", 6]}, {"Zamore v. Whitten": ["8022453", 5]}, {"State v. Carter": ["7942338", 5]}], "S.D.": [2074, {"Wilson v. Great Northern Railway Co.": ["2382379", 16]}, {"State v. McCafferty": ["10665240", 10]}, {"State v. Bult": ["10671606", 8]}, {"Shaffer v. Honeywell, Inc.": ["10690356", 7]}, {"State v. Means": ["10669762", 7]}, {"State, Division of Human Rights ex rel. Miller v. Miller": ["10665901", 7]}, {"In re the Decision of the State Water Management Board Approving Water Permit No. 1791-2": ["10665657", 7]}, {"State v. Dace": ["10676938", 7]}, {"State v. Reiman": ["10684767", 6]}, {"State v. Holter": ["10674516", 6]}], "Cal.": [20030, {"People v. Watson": ["4370142", 69]}, {"People v. Lance W.": ["1949125", 35]}, {"People v. Green": ["2261866", 35]}, {"Auto Equity Sales, Inc. v. Superior Court": ["4375244", 34]}, {"Tarasoff v. Regents of University": ["2292851", 33]}, {"People v. Castro": ["1977065", 30]}, {"Dillon v. Legg": ["2306138", 29]}, {"People v. Dillon": ["4553604", 27]}, {"People v. Wheeler": ["2282118", 27]}, {"Brown v. Brown": ["2272274", 27]}], "Fla.": [19676, {"Hendrix v. State": ["7631031", 154]}, {"State v. Jackson": ["7607106", 135]}, {"Canakaris v. Canakaris": ["9610065", 87]}, {"State v. Mischler": ["7584016", 73]}, {"Jenkins v. State": ["7640202", 60]}, {"Yost v. State": ["7572731", 33]}, {"Florida Patient\u2019s Compensation Fund v. Rowe": ["7625993", 31]}, {"Whitehead v. State": ["7603425", 31]}, {"State v. C.C.": ["7600537", 30]}, {"State v. Neil": ["7613230", 29]}], "N.J.": [8725, {"State v. Roth": ["1350374", 28]}, {"Rova Farms Resort, Inc. v. Investors Insurance Co. of America": ["1930491", 24]}, {"Judson v. Peoples Bank & Trust Co.": ["1341754", 21]}, {"State v. Yarbough": ["1360955", 20]}, {"State v. Hodge": ["1350567", 19]}, {"Suter v. San Angelo Foundry & Machine Co.": ["334186", 18]}, {"In re Wilson": ["334908", 17]}, {"State v. Johnson": ["1922161", 15]}, {"Feldman v. Lederle Laboratories": ["1383951", 15]}, {"State v. Hurd": ["338202", 14]}], "Ohio": [4888, {"C. E. Morris Co. v. Foley Construction Co.": ["6711075", 22]}, {"Mominee v. Scherbarth": ["1825181", 19]}, {"Seasons Coal Co. v. City of Cleveland": ["1815389", 17]}, {"State v. Jenkins": ["1817580", 16]}, {"Temple v. Wean United, Inc.": ["6699203", 15]}, {"Blakemore v. Blakemore": ["1812704", 14]}, {"State v. Dehass": ["1788172", 12]}, {"Harless v. Willis Day Warehousing Co.": ["6710658", 11]}, {"Ady v. West American Insurance": ["1808761", 11]}, {"Mers v. Dispatch Printing Co.": ["1820280", 10]}], "Or.": [5286, {"State v. Middleton": ["2189309", 21]}, {"State v. Kennedy": ["2187197", 16]}, {"State v. Caraher": ["8642324", 14]}, {"State v. Lowry": ["2187222", 14]}, {"Brennen v. City of Eugene": ["2159852", 12]}, {"State v. Cloutier": ["2161207", 11]}, {"Bauman v. State Accident Insurance Fund Corp.": ["2187255", 11]}, {"State v. Westlund": ["4388474", 11]}, {"State v. Van Hooser": ["2130968", 10]}, {"Ball v. Gladden": ["2091903", 10]}], "La.": [20432, {"Arceneaux v. Domingue": ["9638843", 232]}, {"Canter v. Koehring Co.": ["9777719", 141]}, {"State v. Sepulvado": ["9606745", 103]}, {"Reck v. Stevens": ["9586060", 101]}, {"Coco v. Winston Industries, Inc.": ["9678451", 76]}, {"State v. Bonanno": ["9565547", 75]}, {"State v. Smith": ["7638742", 40]}, {"State v. Captville": ["7632921", 38]}, {"State v. Lanclos": ["9536232", 37]}, {"Loescher v. Parr": ["9662386", 32]}], "Tex.": [25110, {"Garza v. Alviar": ["10178160", 99]}, {"Almanza v. State": ["9961798", 96]}, {"King v. King": ["2328399", 86]}, {"City of Houston v. Clear Creek Basin Authority": ["9947817", 80]}, {"Glover v. Texas General Indemnity Co.": ["9970380", 57]}, {"Houston v. State": ["9941925", 54]}, {"Wilson v. State": ["9943636", 46]}, {"Dyson v. Olin Corp.": ["9973361", 45]}, {"Duncan v. Cessna Aircraft Co.": ["9940948", 40]}, {"Allied Finance Co. v. Garza": ["9959348", 39]}], "Minn.": [10049, {"Moylan v. Moylan": ["10658190", 57]}, {"State v. Merrill": ["10686608", 49]}, {"Marriage of Pikula v. Pikula": ["10653187", 41]}, {"Betlach v. Wayzata Condominium": ["10685281", 38]}, {"Gruenhagen v. Larson": ["900816", 26]}, {"Marriage of Rutten v. Rutten": ["10665741", 24]}, {"Nyflot v. Commissioner of Public Safety": ["10654244", 22]}, {"State v. Saldana": ["10673518", 20]}, {"State v. Myers": ["10669732", 20]}, {"State v. Wahlberg": ["10682809", 20]}], "Okla.": [3247, {"Spuehler v. State": ["10411148", 19]}, {"Burks v. State": ["10451255", 15]}, {"Robison v. State": ["10428174", 12]}, {"Davis v. State": ["10431360", 12]}, {"Dutton v. State": ["10430025", 12]}, {"Renfro v. State": ["11211571", 12]}, {"Glass v. State": ["10419128", 11]}, {"Chaney v. State": ["10445438", 10]}, {"Green v. State": ["10420351", 10]}, {"Jones v. State": ["10439879", 9]}], "N.C.": [8108, {"State v. Odom": ["8565416", 33]}, {"State v. Powell": ["8573434", 26]}, {"Johnson v. Phoenix Mutual Life Insurance": ["8561020", 18]}, {"State v. McClain": ["8596105", 18]}, {"Stanback v. Stanback": ["8568312", 17]}, {"State v. Earnhardt": ["8560587", 17]}, {"White v. White": ["4755941", 15]}, {"State v. Blackwelder": ["4761533", 14]}, {"State v. Ahearn": ["8565300", 14]}, {"State v. Bullard": ["4750010", 14]}], "Idaho": [2947, {"State v. Toohill": ["4402463", 29]}, {"Anderson v. Ethington": ["4402415", 15]}, {"State v. Nice": ["4402229", 13]}, {"Leliefeld v. Johnson": ["4403645", 11]}, {"Cheney v. Palos Verdes Investment Corp.": ["4404153", 10]}, {"Rueth v. State": ["4402688", 10]}, {"State v. Reinke": ["4402630", 9]}, {"State v. Newman": ["4450174", 9]}, {"Jackson v. Minidoka Irrigation District": ["4394415", 9]}, {"Stephens v. Stearns": ["4429763", 9]}], "Wis.": [3810, {"Ball v. District No. 4": ["8674970", 32]}, {"Boynton Cab Co. v. Neubeck": ["8680580", 19]}, {"Kollasch v. Adamany": ["8674508", 18]}, {"Brockmeyer v. Dun & Bradstreet": ["8674718", 14]}, {"State v. Woods": ["8675042", 14]}, {"Pierringer v. Hoger": ["8676173", 13]}, {"Wangen v. Ford Motor Co.": ["8673481", 13]}, {"Milwaukee Metropolitan Sewerage District v. Wisconsin Department of Natural Resources": ["8675527", 13]}, {"First National Leasing Corp. v. City of Madison": ["8672446", 12]}, {"Preloznik v. City of Madison": ["8674557", 12]}], "Ky.": [1916, {"Hilen v. Hays": ["9947184", 9]}, {"Ice v. Commonwealth": ["9949961", 7]}, {"Gall v. Commonwealth": ["9927237", 6]}, {"McQueen v. Commonwealth": ["9943158", 6]}, {"Gall v. Commonwealth": ["9959899", 6]}, {"Baker v. Commonwealth": ["11316117", 6]}, {"Ohio Casualty Insurance Co. v. Stanfield": ["9943695", 5]}, {"Deutsch v. Shein": ["9929531", 5]}, {"Payne v. Commonwealth": ["9986633", 5]}, {"Fann v. Mcguffey": ["10139950", 5]}], "Kan.": [3191, {"State v. Marks": ["1443884", 13]}, {"Wooderson v. Ortho Pharmaceutical Corp.": ["1500242", 9]}, {"Toumberlin v. Haas": ["1446065", 9]}, {"Nordstrom v. Miller": ["1456844", 8]}, {"State v. Deskins": ["1485911", 8]}, {"State v. Pink": ["1446077", 8]}, {"State v. Richard": ["1500269", 8]}, {"Roberts v. Saylor": ["1428934", 7]}, {"Johnson v. National Beef Packing Co.": ["88173", 7]}, {"Douglas v. Lombardino": ["1446110", 7]}], "Ariz.": [5209, {"Schweiger v. China Doll Restaurant, Inc.": ["718179", 27]}, {"State v. Chapple": ["737525", 23]}, {"Associated Indemnity Corp. v. Warner": ["745125", 21]}, {"Wagenseller v. Scottsdale Memorial Hospital": ["1470037", 20]}, {"Sparks v. Republic National Life Insurance": ["741384", 19]}, {"State v. Nash": ["745132", 19]}, {"Fuenning v. Superior Court": ["720018", 17]}, {"Kenyon v. Hammer": ["743381", 16]}, {"Darner Motor Sales, Inc. v. Universal Underwriters Insurance": ["1536428", 13]}, {"State v. Lee": ["743419", 13]}], "Ga.": [12741, {"Johnson v. State": ["1155362", 39]}, {"Humphrey v. State": ["1199234", 26]}, {"Flewellen v. Atlanta Casualty Co.": ["1190985", 18]}, {"Williams v. State": ["1195405", 17]}, {"Felker v. State": ["1199302", 17]}, {"Bowen v. State": ["626267", 17]}, {"Momon v. State": ["1187328", 16]}, {"Spivey v. State": ["1201004", 15]}, {"Parks v. State": ["1203771", 15]}, {"Devier v. State": ["1200948", 14]}], "Wash.": [7855, {"State v. Green": ["1164048", 33]}, {"State v. Guloy": ["1201388", 26]}, {"Wilson v. Steinbach": ["1151217", 24]}, {"Hartley v. State": ["1134110", 20]}, {"State v. Ryan": ["1134164", 18]}, {"State v. Dictado": ["1137147", 18]}, {"State v. Ringer": ["1142113", 16]}, {"Ridgeview Properties v. Starbuck": ["1157588", 15]}, {"State ex rel. Carroll v. Junker": ["1070564", 14]}, {"Petersen v. State": ["1142085", 14]}], "Mont.": [2418, {"Cereck v. Albertson\u2019s Inc.": ["2544433", 14]}, {"Klaudt v. Flink": ["2523415", 13]}, {"State v. Liddell": ["2477826", 11]}, {"In re the Marriage of Carlson": ["396093", 11]}, {"Dare v. Montana Petroleum Marketing Co.": ["2479941", 9]}, {"Nicholson v. United Pacific Insurance": ["2496484", 8]}, {"Gibson v. Western Fire Insurance": ["2473394", 7]}, {"Gates v. Life of Montana Insurance": ["2539497", 7]}, {"State v. Robbins": ["2494564", 7]}, {"In re the Marriage of Brown": ["2589662", 7]}], "Ind.": [10309, {"Loyd v. State": ["1825316", 46]}, {"Loyd v. State": ["11071617", 45]}, {"Wagner v. State": ["11040121", 41]}, {"Harris v. State": ["11039550", 40]}, {"White v. State": ["11029835", 39]}, {"Young v. State": ["11034077", 27]}, {"German v. State": ["11055766", 27]}, {"Lowery v. State": ["11040294", 22]}, {"Travelers Indemnity Co. v. Armstrong": ["11051464", 19]}, {"Lowe v. State": ["11054009", 19]}], "Ill.": [22678, {"Pedrick v. Peoria & Eastern Railroad": ["2866138", 56]}, {"People v. Perruquet": ["5809665", 39]}, {"Kelsay v. Motorola, Inc.": ["2994390", 38]}, {"People v. La Pointe": ["3082585", 37]}, {"People v. Albanese": ["3147214", 35]}, {"First Capitol Mortgage Corp. v. Talandis Construction Corp.": ["5426498", 31]}, {"Palmateer v. International Harvester Co.": ["5469094", 29]}, {"People v. Collins": ["3138930", 29]}, {"People v. Pickett": ["2933485", 27]}, {"People v. King": ["5463653", 26]}], "N.M.": [2921, {"Sanchez v. Homestake Mining Co.": ["1580019", 12]}, {"State v. Casteneda": ["1555168", 11]}, {"State v. Fish": ["1580008", 10]}, {"Gutierrez v. City of Gallup": ["1580037", 9]}, {"State v. Crespin": ["1573065", 8]}, {"Lee v. Lee": ["1588533", 8]}, {"Albuquerque National Bank v. Albuquerque Ranch Estates, Inc.": ["1584592", 8]}, {"Vaughn v. United Nuclear Corp.": ["1582445", 8]}, {"United Nuclear Corp. v. General Atomic Co.": ["1577300", 7]}, {"Vigil v. Arzola": ["1580114", 7]}], "D.C.": [3365, {"M. A. P. v. Ryan": ["8064389", 23]}, {"Johnson v. United States": ["7977143", 20]}, {"Watts v. United States": ["8011007", 18]}, {"Springer v. United States": ["8014750", 13]}, {"Nader v. de Toledano": ["7955157", 12]}, {"United States v. Edwards": ["8002650", 9]}, {"Copeland v. Marshall": ["5686066", 9]}, {"Christian v. United States": ["8008622", 9]}, {"Peoples Drug Stores, Inc. v. District of Columbia": ["7991970", 9]}, {"Edmund J. Flynn Co. v. LaVay": ["7974916", 8]}], "Pa.": [18227, {"Commonwealth v. Wright": ["1794020", 31]}, {"Standard Venetian Blind Co. v. American Empire Insurance": ["1785950", 29]}, {"Geary v. United States Steel Corp.": ["584439", 28]}, {"Dilliplaine v. Lehigh Valley Trust Co.": ["477868", 26]}, {"Rivenbark v. Commonwealth, Pennsylvania Board of Probation & Parole": ["1795390", 24]}, {"Commonwealth ex rel. Washington v. Maroney": ["1910363", 23]}, {"Sinn v. Burd": ["1757610", 22]}, {"Cathcart v. Keene Industrial Insulation": ["595564", 21]}, {"Commonwealth v. Hubbard": ["1727744", 20]}, {"Commonwealth v. Pierce": ["639130", 20]}], "Colo.": [5061, {"Palmer v. A.H. Robins Co.": ["10416810", 17]}, {"People v. Lowe": ["10435398", 15]}, {"People v. Haymaker": ["10405830", 14]}, {"People v. Abbott": ["10426500", 13]}, {"People v. Rubanowitz": ["10414363", 13]}, {"Page v. Clark": ["2367311", 12]}, {"People v. Thiret": ["10415287", 12]}, {"People v. Taggart": ["10443742", 11]}, {"Metropolitan Gas Repair Service, Inc. v. Kulik": ["10441900", 10]}, {"Stull v. People": ["77744", 9]}], "N.D.": [1803, {"Arneson v. Olson": ["10686471", 9]}, {"Schadler v. Job Service North Dakota": ["10666049", 7]}, {"Lang v. Bank of North Dakota": ["10641943", 7]}, {"Norgaard v. Nodak Mutual Insurance Co.": ["10775713", 6]}, {"Milbank Mutual Insurance Co. v. Dairyland Insurance Co.": ["10653723", 6]}, {"State Bank of Towner v. Hansen": ["10682309", 6]}, {"Miller v. Schwartz": ["10671836", 6]}, {"Gowin v. Hazen Memorial Hospital Ass'n": ["10665451", 6]}, {"Moser v. North Dakota State Highway Commissioner": ["10654988", 6]}, {"Olson v. Job Service North Dakota": ["10628892", 6]}], "S.C.": [3038, {"Townes Associates, Ltd. v. City of Greenville": ["2141069", 23]}, {"Shaluly v. Shaluly": ["8714332", 13]}, {"Lark v. Bi-Lo, Inc.": ["2155305", 11]}, {"Nienow v. Nienow": ["2138292", 9]}, {"Atkinson v. Atkinson": ["2151601", 9]}, {"Smith v. Smith": ["2150056", 9]}, {"State v. Copeland": ["2152905", 8]}, {"McCall ex rel. Andrews v. Batson": ["2165750", 8]}, {"Mylin v. Allen-White Pontiac, Inc.": ["2163257", 8]}, {"Hussey v. Hussey": ["2150198", 8]}], "Conn.": [7710, {"State v. Evans": ["511985", 84]}, {"State v. Leecan": ["558177", 31]}, {"State v. Stepney": ["682797", 27]}, {"State v. Kurvin": ["515860", 25]}, {"Pandolphe\u2019s Auto Parts, Inc. v. Town of Manchester": ["1952604", 24]}, {"State v. Torrence": ["692425", 22]}, {"State v. Morrill": ["695305", 21]}, {"State v. Scielzo": ["679031", 21]}, {"State v. Jones": ["557032", 21]}, {"State v. McKnight": ["682754", 21]}], "Ark.": [3684, {"Dixon v. State": ["1616825", 11]}, {"Norton v. Nat. Bank of Commerce": ["1727450", 11]}, {"Berna v. State": ["1740879", 9]}, {"Day v. Day": ["1742375", 9]}, {"Henry v. State": ["1748066", 8]}, {"Rector v. State": ["1744818", 7]}, {"Walker v. State": ["1880012", 7]}, {"Jones v. State": ["1712552", 7]}, {"Novak v. State": ["1876561", 7]}, {"M.B.M. Co. v. Counce": ["1715529", 6]}], "Neb.": [3409, {"Guggenmos v. Guggenmos": ["5459592", 16]}, {"State v. Tweedy": ["2953422", 9]}, {"State v. Craig": ["5811973", 9]}, {"State v. Reeves": ["5446989", 8]}, {"State v. Hochstein": ["5445090", 8]}, {"State v. Buchanan": ["5417688", 8]}, {"State v. Gregory": ["2882853", 8]}, {"Parsons v. Parsons": ["5816084", 8]}, {"State v. Joy": ["2880110", 8]}, {"State v. Hunt": ["2883022", 7]}], "P.R.": [1072, {"Valle v. American International Insurance": ["8813847", 8]}, {"Zachry International of Puerto Rico, Inc. v. Tribunal Superior de Puerto Rico": ["8813083", 7]}, {"In re Col\u00f3n de Zengotita": ["8757879", 6]}, {"Ramos Villanueva v. Cintr\u00f3n": ["8811841", 5]}, {"In re D\u00edaz Alonso": ["8759385", 5]}, {"Pueblo v. L\u00f3pez P\u00e9rez": ["8813642", 5]}, {"In re Boscio Monllor": ["8759961", 5]}, {"In re Rivera Lassen": ["8757974", 5]}, {"Jim\u00e9nez v. Pelegrina Espinet": ["8812238", 4]}, {"Marina Industrial, Inc. v. Brown Boveri Corp.": ["8756396", 4]}], "Va.": [3189, {"Womack v. Eldridge": ["2123160", 17]}, {"Bates v. Devers": ["2120117", 9]}, {"Higginbotham v. Commonwealth": ["2124970", 9]}, {"Locke v. Johns-Manville Corp.": ["2138751", 9]}, {"First Virginia Bank-Colonial v. Baker": ["2078336", 8]}, {"Hughes v. Moore": ["2120229", 8]}, {"Tuggle v. Commonwealth": ["2069041", 8]}, {"Thomasson v. Thomasson": ["2078373", 8]}, {"LeVasseur v. Commonwealth": ["2078361", 7]}, {"Chaves v. Johnson": ["2069067", 7]}], "Vt.": [1009, {"State v. Jewett": ["4760636", 16]}, {"Lent v. Huntoon": ["4728296", 6]}, {"Sheltra v. Smith": ["8544703", 6]}, {"Hay v. Medical Center Hospital": ["4746024", 6]}, {"State v. Nash": ["4738803", 6]}, {"Darken v. Mooney": ["4736746", 6]}, {"South Burlington School District v. Calcagni-Frazier-Zajchowski Architects, Inc.": ["4718505", 5]}, {"State v. Foy": ["4736843", 5]}, {"Cliche v. Cliche": ["4728000", 5]}, {"Gramatan Home Investors Corp. v. Starling": ["4728630", 5]}], "Tenn.": [2565, {"State v. Cabbage": ["9951632", 14]}, {"State v. Hatchett": ["9947403", 11]}, {"Gray v. State": ["10131084", 11]}, {"Williams v. State": ["9971725", 10]}, {"McCroskey v. Bryant Air Conditioning Co.": ["10127107", 8]}, {"Harmon v. Angus R. Jessup Associates, Inc.": ["9975561", 6]}, {"Baxter v. Rose": ["10141111", 6]}, {"State v. Dicks": ["9958832", 6]}, {"Duffy v. State": ["9933053", 6]}, {"Harrison v. Schrader": ["9951842", 5]}], "Iowa": [3912, {"Taylor v. State": ["10672484", 12]}, {"State v. Hall": ["10680542", 9]}, {"Goetzman v. Wichern": ["10677705", 8]}, {"Lewis v. State": ["12021668", 7]}, {"Beier Glass Co. v. Brundige": ["10673954", 7]}, {"State v. Myers": ["10656129", 7]}, {"Citizens Savings Bank v. Sac City State Bank": ["10674931", 7]}, {"Budding v. Iowa Department of Job Service": ["10671405", 7]}, {"State v. Morrison": ["10674620", 7]}, {"Henkel v. R & S Bottling Co.": ["10673859", 6]}], "Mich.": [8414, {"People v. Coles": ["1973374", 38]}, {"Toussaint v. Blue Cross & Blue Shield": ["1950983", 36]}, {"Ross v. Consumers Power Co.": ["1968430", 34]}, {"Cassidy v. McGovern": ["1976720", 23]}, {"Rizzo v. Kretschmer": ["1907455", 22]}, {"Moning v. Alfono": ["1926695", 19]}, {"People v. Hampton": ["1953104", 17]}, {"Williams v. Payne": ["2249901", 15]}, {"Abel v. Eli Lilly & Co.": ["1971483", 14]}, {"Tuttle v. Department of State Highways": ["1932826", 14]}], "Alaska": [2172, {"McClain v. State": ["10478496", 28]}, {"State v. Chaney": ["10562536", 18]}, {"State v. Andrews": ["10417214", 12]}, {"Pears v. State": ["10421389", 11]}, {"Morrow v. New Moon Homes, Inc.": ["10459055", 8]}, {"Dura Corp. v. Harned": ["10409519", 8]}, {"Cooksey v. State": ["10480192", 8]}, {"Lerchenstein v. State": ["10412022", 8]}, {"Juneby v. State": ["10420692", 8]}, {"Juneby v. State": ["10438523", 8]}], "R.I.": [1601, {"Casey v. Casey": ["7912050", 10]}, {"Denardo v. Fairmount Foundries Cranston, Inc.": ["3184366", 9]}, {"City of Warwick v. Aptt": ["7920488", 7]}, {"Barratt v. Burlingham": ["7925522", 6]}, {"Ryan v. State, Department of Transportation": ["7986951", 6]}, {"Emmett v. Town of Coventry": ["7925469", 6]}, {"Wordell v. Wordell": ["7990039", 6]}, {"Hughes v. Saco Casting Co.": ["8005360", 5]}, {"Laird v. Chrysler Corp.": ["7950263", 5]}, {"Presley v. Newport Hospital": ["3109674", 5]}], "Nev.": [933, {"Smith v. State": ["2404860", 6]}, {"McGuire v. State": ["2412192", 6]}, {"Paradise Palms Community Ass'n v. Paradise Homes": ["4868151", 5]}, {"Goldsworthy v. Hannifin": ["4845056", 5]}, {"Nevius v. State": ["2404079", 5]}, {"Bishop v. State": ["4804343", 5]}, {"Udevco, Inc. v. Wagner": ["2410628", 5]}, {"Continental Insurance v. Moseley": ["2410757", 4]}, {"K-Mart Corp. v. State Industrial Insurance System": ["2406980", 4]}, {"General Electric Co. v. Bush": ["4819954", 4]}], "Ala.": [11868, {"Beck v. State": ["9561497", 25]}, {"McLendon v. McLendon": ["7621463", 19]}, {"Boatwright v. State": ["7617631", 17]}, {"Chavers v. State": ["9736290", 16]}, {"Shadle v. State": ["2596005", 13]}, {"Moore v. State, Department of Pensions & Security": ["7624539", 13]}, {"Williams v. State": ["7624681", 13]}, {"Thompson v. Hartford Accident & Indemnity Co.": ["7637792", 13]}, {"Bush v. State": ["9527564", 12]}, {"Kennedy v. State": ["7625289", 12]}], "Md.": [5539, {"Tichnell v. State": ["2089250", 18]}, {"Ramsay, Scarlett & Co. v. Comptroller of Treasury": ["1976080", 17]}, {"Lodowski v. State": ["1976074", 16]}, {"Foster v. State": ["2057586", 13]}, {"Dorsey v. State": ["1881315", 13]}, {"Johnson v. State": ["2055530", 11]}, {"Walczak v. State": ["1976084", 10]}, {"Adler v. American Standard Corp.": ["2097248", 9]}, {"Attorney General of Maryland v. Waldron": ["2093698", 9]}, {"Scott v. Watson": ["1884521", 9]}], "Wyo.": [2870, {"Martinez v. State": ["10449482", 22]}, {"Hopkinson v. State": ["10437213", 16]}, {"Abas v. State ex rel. Wyoming Worker\u2019s Compensation Division": ["10425848", 12]}, {"Mountain Fuel Supply Co. v. Public Service Commission": ["10431148", 11]}, {"Garner v. Hickman": ["10414144", 10]}, {"Scheikofsky v. State": ["10440087", 10]}, {"McClellan v. Tottenhoff": ["10425148", 9]}, {"Jahnke v. State": ["11341970", 9]}, {"Smith v. State": ["10468792", 9]}, {"Cates v. Eddy": ["10428373", 9]}], "N.H.": [1772, {"State v. Ball": ["4405831", 24]}, {"Monge v. Beebe Rubber Co.": ["1294859", 16]}, {"State v. Sands": ["2348611", 15]}, {"Carson v. Maurer": ["4450123", 12]}, {"Daboul v. Town of Hampton": ["4405661", 9]}, {"Cloutier v. Great Atlantic & Pacific Tea Co.": ["4452312", 8]}, {"Corso v. Merrill": ["4448427", 7]}, {"State v. Ruelke": ["4442202", 7]}, {"Lawton v. Great Southwest Fire Insurance": ["4444650", 6]}, {"White v. Lee": ["4405605", 6]}], "Del.": [1216, {"Weinberger v. UOP, Inc.": ["7989484", 22]}, {"Aronson v. Lewis": ["7988323", 17]}, {"Revlon, Inc. v. MacAndrews & Forbes Holdings, Inc.": ["7908169", 16]}, {"Smith v. Van Gorkom": ["7967423", 15]}, {"Moran v. Household International, Inc.": ["7909045", 13]}, {"Unocal Corp. v. Mesa Petroleum Co.": ["7918461", 12]}, {"Shields v. Shields": ["7912853", 9]}, {"Pogostin v. Rice": ["7902916", 9]}, {"Rabkin v. Philip A. Hunt Chemical Corp.": ["7920538", 8]}, {"Riley v. State": ["11321358", 6]}], "Haw.": [798, {"Leong ex rel. Petagno v. Takasaki": ["1470084", 11]}, {"State v. Kim": ["1432311", 9]}, {"Hulsman v. Hemmeter Development Corp.": ["1433838", 8]}, {"Parnar v. Americana Hotels, Inc.": ["1433860", 7]}, {"Pickard v. City of Honolulu": ["1451503", 6]}, {"McKenna v. Aktiengesellschaft": ["1471996", 6]}, {"Rodrigues v. State": ["8829366", 5]}, {"Namauu v. City & County of Honolulu": ["8829829", 5]}, {"McKeague v. Talbert": ["3374393", 5]}, {"Sturla, Inc. v. Fireman\u2019s Fund Insurance": ["1427844", 4]}], "Utah": [1963, {"Utah Department of Administrative Services v. Public Service Commission": ["10430566", 10]}, {"State v. McCardell": ["10435962", 10]}, {"State v. Tucker": ["10412295", 8]}, {"Salt Lake City Corp. v. Department of Employment Security": ["10435836", 8]}, {"State v. Petree": ["10428806", 7]}, {"State v. Wulffenstein": ["10428177", 7]}, {"State v. Pierre": ["10473527", 6]}, {"Ballard v. State, Motor Vehicle Division": ["10461087", 6]}, {"State v. Chambers": ["10412412", 6]}, {"State v. Norton": ["10424759", 6]}], "W. Va.": [2602, {"State ex rel. Adkins v. Sims": ["8583874", 16]}, {"Harless v. First National Bank in Fairmont": ["8578936", 14]}, {"State v. Thomas": ["8580802", 13]}, {"Nelson v. West Virginia Public Employees Insurance Board": ["8579804", 13]}, {"Allen v. State of West Virginia Human Rights Commission": ["8578278", 9]}, {"Mandolidis v. Elkins Industries, Inc.": ["8580246", 8]}, {"State v. Sheppard": ["8580177", 8]}, {"State ex rel. Kucera v. City of Wheeling": ["8581858", 8]}, {"West Virginia Citizens Action Group, Inc. v. Daley": ["8578852", 7]}, {"Pauley v. Kelly": ["8580196", 7]}], "Dakota Territory": [4, {"Champion v. Board of County Commissioners of Minnehaha County": ["8586935", 1]}, {"Oswald v. McCauley": ["2605952", 1]}, {"Pielke v. Chicago, M. & St. P. Ry. Co.": ["8586947", 1]}, {"Pierre Water-Works Co. v. Hughes County": ["8586681", 1]}], "V.I.": [58, {"Zugelter v. Bank of America National Trust & Savings Ass'n": ["1070322", 2]}, {"Leonard v. Government of the Virgin Islands": ["1075141", 2]}, {"Richardson v. Virgin Islands Housing Authority": ["1071615", 2]}, {"Pickering v. Government of the Virgin Islands": ["1070380", 2]}, {"Webster v. Government of the Virgin Islands": ["1075223", 2]}, {"Mercer v. Government of the Virgin Islands": ["1071680", 2]}, {"Benjamin v. Government of the Virgin Islands": ["1071584", 2]}, {"Homer v. Lorillard": ["1119615", 2]}, {"Richards v. Election Committee of St. Thomas-St. John American Federation of Teachers": ["1104485", 2]}, {"Weems v. Petersen": ["1070481", 2]}], "Guam": [2, {"People v. Aguon": ["5311674", 1]}, {"People v. Rico": ["5312386", 1]}]}